Workbook

Sheet Sheet1
A3: Product | B3: Sales | C3: Region | D3: Discount Eligible | F3: Check if Sales > 100 | G3: Test if Region = 'East' | H3: Check if Sales > 100 AND Region = 'East' | I3: Check if Sales < 100 OR Region = 'West' | J3: Check if Sales > 100 AND < 200 | K3: Check if Sales < 100 OR Region = North | L3: Check if Region = East AND Discount Eligible = 'Yes' | M3: Return Pass/Fail if Sales > 150 AND Region = East | N3: Categorize Region as 'Main' if East, otherwise 'Other' | O3: Check if Sales > 100 AND (Region = East OR Region = West) | P3: Mark Review if Sales < 100 OR Region = North | Q3: Apply 10% discount if Sales > 150 AND Region = East | R3: Check if three conditions hold (Sales > 100, Region = East, Discount Eligible = Yes) | S3: Mark 'Priority' if Sales > 200 OR (Sales > 100 AND Region = East) | T3: Flag mid-tier sales (Sales > 100 and < 200, but not East) | U3: Nested AND inside OR for discount rules | V3: Use nested IFs for tiered logic
A4: A | B4: 120 | C4: East | D4: Yes | F4: =IF(B4>100,TRUE,FALSE) -> TRUE | G4: =IF(C4="East",TRUE,FALSE) -> TRUE | H4: =IF(AND(B4>100, C4="East"), TRUE, FALSE) -> TRUE | I4: =IF(OR(B4<100, C4="West"), TRUE, FALSE) -> FALSE | J4: =IF(AND(B4>100,B4<200),TRUE,FALSE) -> TRUE | K4: =IF(OR(B4<100,C4="North"),TRUE,FALSE) -> FALSE | L4: =IF(AND(C4="East",D4="Yes"),TRUE,FALSE) -> TRUE | M4: =IF(AND(B4>150,C4="East"),"Pass","Fail") -> Fail | N4: =IF(C4="East","Main","Other") -> Main | O4: =IF(AND(OR(B4>100,C4="East",C4="West")),TRUE,FALSE) -> TRUE | P4: =IF(OR(B4<100,C4="North"),"Review","Ok") -> Ok | Q4: =IF(AND(B4>150,C4="East"),B4*0.9,) -> 0 | R4: =IF(AND(B4>100,C4="East",D4="Yes"),TRUE,FALSE) -> TRUE | S4: =IF(OR(B4>200,AND(B4>100,C4="East")),"Priority","Normal") -> Priority | T4: =IF(AND(B4>100,B4<200,C4<>"East"),TRUE,FALSE) -> FALSE | U4: =OR(AND(B4>150, C4="East"), AND(B4>200, C4="West")) -> FALSE | V4: =IF(AND(B2>200,C2="East"),"High",IF(AND(B2>100,C2="West"),"Medium","Low")) -> Low
A5: B | B5: 90 | C5: West | D5: No | F5: =IF(B5>100,TRUE,FALSE) -> FALSE | G5: =IF(C5="East",TRUE,FALSE) -> FALSE | H5: =IF(AND(B5>100, C5="East"), TRUE, FALSE) -> FALSE | I5: =IF(OR(B5<100, C5="West"), TRUE, FALSE) -> TRUE | J5: =IF(AND(B5>100,B5<200),TRUE,FALSE) -> FALSE | K5: =IF(OR(B5<100,C5="North"),TRUE,FALSE) -> TRUE | L5: =IF(AND(C5="East",D5="Yes"),TRUE,FALSE) -> FALSE | M5: =IF(AND(B5>150,C5="East"),"Pass","Fail") -> Fail | N5: =IF(C5="East","Main","Other") -> Other | O5: =IF(AND(OR(B5>100,C5="East",C5="West")),TRUE,FALSE) -> TRUE | P5: =IF(OR(B5<100,C5="North"),"Review","Ok") -> Review | Q5: =IF(AND(B5>150,C5="East"),B5*0.9,) -> 0 | R5: =IF(AND(B5>100,C5="East",D5="Yes"),TRUE,FALSE) -> FALSE | S5: =IF(OR(B5>200,AND(B5>100,C5="East")),"Priority","Normal") -> Normal | T5: =IF(AND(B5>100,B5<200,C5<>"East"),TRUE,FALSE) -> FALSE | U5: =OR(AND(B5>150, C5="East"), AND(B5>200, C5="West")) -> FALSE | V5: =IF(AND(B3>200,C3="East"),"High",IF(AND(B3>100,C3="West"),"Medium","Low")) -> Low
A6: C | B6: 200 | C6: East | D6: Yes | F6: =IF(B6>100,TRUE,FALSE) -> TRUE | G6: =IF(C6="East",TRUE,FALSE) -> TRUE | H6: =IF(AND(B6>100, C6="East"), TRUE, FALSE) -> TRUE | I6: =IF(OR(B6<100, C6="West"), TRUE, FALSE) -> FALSE | J6: =IF(AND(B6>100,B6<200),TRUE,FALSE) -> FALSE | K6: =IF(OR(B6<100,C6="North"),TRUE,FALSE) -> FALSE | L6: =IF(AND(C6="East",D6="Yes"),TRUE,FALSE) -> TRUE | M6: =IF(AND(B6>150,C6="East"),"Pass","Fail") -> Pass | N6: =IF(C6="East","Main","Other") -> Main | O6: =IF(AND(OR(B6>100,C6="East",C6="West")),TRUE,FALSE) -> TRUE | P6: =IF(OR(B6<100,C6="North"),"Review","Ok") -> Ok | Q6: =IF(AND(B6>150,C6="East"),B6*0.9,) -> 180 | R6: =IF(AND(B6>100,C6="East",D6="Yes"),TRUE,FALSE) -> TRUE | S6: =IF(OR(B6>200,AND(B6>100,C6="East")),"Priority","Normal") -> Priority | T6: =IF(AND(B6>100,B6<200,C6<>"East"),TRUE,FALSE) -> FALSE | U6: =OR(AND(B6>150, C6="East"), AND(B6>200, C6="West")) -> TRUE | V6: =IF(AND(B4>200,C4="East"),"High",IF(AND(B4>100,C4="West"),"Medium","Low")) -> Low
A7: D | B7: 150 | C7: North | D7: No | F7: =IF(B7>100,TRUE,FALSE) -> TRUE | G7: =IF(C7="East",TRUE,FALSE) -> FALSE | H7: =IF(AND(B7>100, C7="East"), TRUE, FALSE) -> FALSE | I7: =IF(OR(B7<100, C7="West"), TRUE, FALSE) -> FALSE | J7: =IF(AND(B7>100,B7<200),TRUE,FALSE) -> TRUE | K7: =IF(OR(B7<100,C7="North"),TRUE,FALSE) -> TRUE | L7: =IF(AND(C7="East",D7="Yes"),TRUE,FALSE) -> FALSE | M7: =IF(AND(B7>150,C7="East"),"Pass","Fail") -> Fail | N7: =IF(C7="East","Main","Other") -> Other | O7: =IF(AND(OR(B7>100,C7="East",C7="West")),TRUE,FALSE) -> TRUE | P7: =IF(OR(B7<100,C7="North"),"Review","Ok") -> Review | Q7: =IF(AND(B7>150,C7="East"),B7*0.9,) -> 0 | R7: =IF(AND(B7>100,C7="East",D7="Yes"),TRUE,FALSE) -> FALSE | S7: =IF(OR(B7>200,AND(B7>100,C7="East")),"Priority","Normal") -> Normal | T7: =IF(AND(B7>100,B7<200,C7<>"East"),TRUE,FALSE) -> TRUE | U7: =OR(AND(B7>150, C7="East"), AND(B7>200, C7="West")) -> FALSE | V7: =IF(AND(B5>200,C5="East"),"High",IF(AND(B5>100,C5="West"),"Medium","Low")) -> Low
A8: E | B8: 80 | C8: East | D8: Yes | F8: =IF(B8>100,TRUE,FALSE) -> FALSE | G8: =IF(C8="East",TRUE,FALSE) -> TRUE | H8: =IF(AND(B8>100, C8="East"), TRUE, FALSE) -> FALSE | I8: =IF(OR(B8<100, C8="West"), TRUE, FALSE) -> TRUE | J8: =IF(AND(B8>100,B8<200),TRUE,FALSE) -> FALSE | K8: =IF(OR(B8<100,C8="North"),TRUE,FALSE) -> TRUE | L8: =IF(AND(C8="East",D8="Yes"),TRUE,FALSE) -> TRUE | M8: =IF(AND(B8>150,C8="East"),"Pass","Fail") -> Fail | N8: =IF(C8="East","Main","Other") -> Main | O8: =IF(AND(OR(B8>100,C8="East",C8="West")),TRUE,FALSE) -> TRUE | P8: =IF(OR(B8<100,C8="North"),"Review","Ok") -> Review | Q8: =IF(AND(B8>150,C8="East"),B8*0.9,) -> 0 | R8: =IF(AND(B8>100,C8="East",D8="Yes"),TRUE,FALSE) -> FALSE | S8: =IF(OR(B8>200,AND(B8>100,C8="East")),"Priority","Normal") -> Normal | T8: =IF(AND(B8>100,B8<200,C8<>"East"),TRUE,FALSE) -> FALSE | U8: =OR(AND(B8>150, C8="East"), AND(B8>200, C8="West")) -> FALSE | V8: =IF(AND(B6>200,C6="East"),"High",IF(AND(B6>100,C6="West"),"Medium","Low")) -> Low

Sheet Identifying the least revenue
A1: Product ID | B1: Product Name | C1: Category | D1: Units Sold | E1: Price Per Unit | F1: Total Revenue
A2: P001 | B2: Smartphone A | C2: Electronics | D2: 150 | E2: 10000 | F2: 1500000
A3: P002 | B3: Headphones C | C3: Electronics | D3: 300 | E3: 1500 | F3: 450000
A4: P003 | B4: T-shirt D | C4: Fashion | D4: 500 | E4: 500 | F4: 250000
A5: P004 | B5: Book F | C5: Books | D5: 1000 | E5: 200 | F5: 200000
A6: P005 | B6: Toy H | C6: Toys | D6: 150 | E6: 1000 | F6: 150000
A8: Answer | B8: =MIN(F2:F6) -> 150000

Sheet Urban Company
A1: Customer Name | B1: Address | C1: Cleaned Customer Name | D1: Cleaned Address
A2: Aman Sharma | B2: 123,Mg Road, Delhi | C2: =TRIM(A2) -> Aman Sharma | D2: =TRIM(B2) -> 123,Mg Road, Delhi
A3: Priya Verma | B3: 456, Brigade Road, Bangalore | C3: =TRIM(A3) -> Priya Verma | D3: =TRIM(B3) -> 456, Brigade Road, Bangalore
A4: Rajesh Kumar | B4: 789, Anna Salai, Chennai | C4: =TRIM(A4) -> Rajesh Kumar | D4: =TRIM(B4) -> 789, Anna Salai, Chennai
A5: Sunita Reddy | B5: 1010, Park Street, Kolkata | C5: =TRIM(A5) -> Sunita Reddy | D5: =TRIM(B5) -> 1010, Park Street, Kolkata
A6: Vijay Singh | B6: 1111, Banjara Hills, Hyderabad | C6: =TRIM(A6) -> Vijay Singh | D6: =TRIM(B6) -> 1111, Banjara Hills, Hyderabad

Sheet Meta Ad Revenue Analysis
A1: State | B1: Ad Clicks | C1: Revenue | D1: Corrected revenue
A2: Maharashtra | B2: 1200 | C2: 10000 | D2: =IFERROR(C2,500) -> 10000
A3: Karnataka | B3: 800 | C3: 7000 | D3: =IFERROR(C3,500) -> 7000
A4: Tamil Nadu | B4: 950 | C4: #DIV/0! | D4: =IFERROR(C4,500) -> 500
A5: Kerala | B5: 1100 | C5: 8500 | D5: =IFERROR(C5,500) -> 8500

Sheet Subscription Billing Time
A1: Customer Name | B1: Hours | C1: Minutes | D1: Billing Time
A2: Reliance | B2: 10 | C2: 30 | D2: =TIME(B2,C2,0) -> 0.4375
A3: TCS | B3: 12 | C3: 45 | D3: =TIME(B3,C3,0) -> 0.53125
A4: Infosys | B4: 14 | C4: 15 | D4: =TIME(B4,C4,0) -> 0.59375
A5: HDFC Bank | B5: 16 | C5: 0 | D5: =TIME(B5,C5,0) -> 0.66666667
A6: ICICI Bank | B6: 18 | C6: 30 | D6: =TIME(B6,C6,0) -> 0.77083333

Sheet Converting Sales Data
A1: Seller ID | B1: Seller Name | C1: Sales Figure(Text) | D1: Sales Figure(Number)
A2: 101 | B2: Ram Trading Co. | C2: 10000 | D2: =_xlfn.NUMBERVALUE(C2) -> 10000
A3: 102 | B3: MAHESH Enterprises | C3: 15000 | D3: =_xlfn.NUMBERVALUE(C3) -> 15000
A4: 103 | B4: Vinayaka STORES | C4: 20000 | D4: =_xlfn.NUMBERVALUE(C4) -> 20000
A5: 104 | B5: Anand & Sons | C5: 25000 | D5: =_xlfn.NUMBERVALUE(C5) -> 25000
A6: 105 | B6: Shree Ganesh Mart | C6: 30000 | D6: =_xlfn.NUMBERVALUE(C6) -> 30000

Sheet Vehicle Price Analysis
A1: Vehicle Id | B1: Price (INR)
A2: V001 | B2: 350000
A3: V002 | B3: 450000
A4: V003 | B4: 300000
A5: V004 | B5: 500000
A6: V005 | B6: 600000
A7: V006 | B7: 700000
A8: V007 | B8: 550000
A9: V008 | B9: 400000
A10: V009 | B10: 380000
A11: V010 | B11: 620000
A14: 25th Percentile | B14: =QUARTILE(B2:B11,1) -> 385000
A15: 50th Percentile | B15: =QUARTILE(B2:B11,2) -> 475000
A16: 75th Percentile | B16: =QUARTILE(B2:B11,3) -> 587500

Sheet Customer Support Tickets
A1: Region | B1: Support Tickets Received
A2: North | B2: 150
A3: South | B3: 120
A4: East | B4: 100
A5: West | B5: 80
A6: Central | B6: 50
A8: Answer | B8: =SUM(B2:B6) -> 500

Sheet Calculating Revenue Loss
A1: Item Id | B1: Item Name | C1: Units Requested | D1: Units Available | E1: Price per Unit | F1: Revenue Loss
A2: 101 | B2: Denim Jacket | C2: 500 | D2: 300 | E2: 1500 | F2: =(C2-D2)*E2 -> 300000
A3: 102 | B3: Leather Boots | C3: 200 | D3: 200 | E3: 3500 | F3: =(C3-D3)*E3 -> 0
A4: 103 | B4: Summer Dress | C4: 450 | D4: 400 | E4: 1200 | F4: =(C4-D4)*E4 -> 60000
A5: 104 | B5: Casual Dress | C5: 600 | D5: 550 | E5: 800 | F5: =(C5-D5)*E5 -> 40000
A6: 105 | B6: Formal Trousers | C6: 300 | D6: 250 | E6: 2000 | F6: =(C6-D6)*E6 -> 100000

Sheet Analysis of Ad Campaign
A1: Campaign Name | B1: Impressions | C1: Clicks | D1: Conversions | E1: Cost | F1: Revenue | G1: Conversion Rate % | H1: Cost per Click (CPC) | I1: Return On Investment
A2: Campaign A | B2: 12500 | C2: 380 | D2: 25 | E2: 35000 | F2: 175000 | G2: =(D2/C2)*100 -> 6.5789474 | H2: =B2/C2 -> 32.894737 | I2: =((F2-E2)/E2)*100 -> 400
A3: Campaign B | B3: 9800 | C3: 290 | D3: 20 | E3: 28000 | F3: 168000 | G3: =(D3/C3)*100 -> 6.8965517 | H3: =B3/C3 -> 33.793103 | I3: =((F3-E3)/E3)*100 -> 500
A4: Campaign C | B4: 15000 | C4: 420 | D4: 30 | E4: 40000 | F4: 50000 | G4: =(D4/C4)*100 -> 7.1428571 | H4: =B4/C4 -> 35.714286 | I4: =((F4-E4)/E4)*100 -> 25
A5: Campaign D | B5: 8000 | C5: 250 | D5: 15 | E5: 22000 | F5: 44000 | G5: =(D5/C5)*100 -> 6 | H5: =B5/C5 -> 32 | I5: =((F5-E5)/E5)*100 -> 100
A6: Campaign E | B6: 20000 | C6: 600 | D6: 40 | E6: 50000 | F6: 100000 | G6: =(D6/C6)*100 -> 6.6666667 | H6: =B6/C6 -> 33.333333 | I6: =((F6-E6)/E6)*100 -> 100
A7: Campaign F | B7: 13500 | C7: 410 | D7: 28 | E7: 37000 | F7: 74000 | G7: =(D7/C7)*100 -> 6.8292683 | H7: =B7/C7 -> 32.926829 | I7: =((F7-E7)/E7)*100 -> 100
A8: Campaign G | B8: 11000 | C8: 320 | D8: 18 | E8: 30000 | F8: 40000 | G8: =(D8/C8)*100 -> 5.625 | H8: =B8/C8 -> 34.375 | I8: =((F8-E8)/E8)*100 -> 33.333333
A9: Campaign H | B9: 16500 | C9: 480 | D9: 35 | E9: 45000 | F9: 180000 | G9: =(D9/C9)*100 -> 7.2916667 | H9: =B9/C9 -> 34.375 | I9: =((F9-E9)/E9)*100 -> 300
A10: Campaign I | B10: 7500 | C10: 200 | D10: 12 | E10: 18000 | F10: 72000 | G10: =(D10/C10)*100 -> 6 | H10: =B10/C10 -> 37.5 | I10: =((F10-E10)/E10)*100 -> 300
A11: Campaign J | B11: 18000 | C11: 550 | D11: 45 | E11: 60000 | F11: 300000 | G11: =(D11/C11)*100 -> 8.1818182 | H11: =B11/C11 -> 32.727273 | I11: =((F11-E11)/E11)*100 -> 400
A15: Top Performing Campaign Based on ROI | E15: =INDEX(A2:A11,MATCH(MAX(I2:I11),I2:I11,0)) -> Campaign B
A16: Top Performing Campaign Based on Revnue | E16: =INDEX(A2:A11,MATCH(MAX(I2:I11),I2:I11,0)) -> Campaign B
A17: Least Performing Campaign Based on ROI | E17: =INDEX(A2:A11,MATCH(MIN(I2:I11),I2:I11,0)) -> Campaign C
A18: Least Performing Campaign Based on Revenue | E18: =INDEX(A2:A11,MATCH(MIN(F2:F11),F2:F11,0)) -> Campaign G

Sheet Tracking In-App Purchases
A1: Transaction ID | B1: User ID | C1: Amount Spent (In Rupees) | D1: Amount Spent Whole Number
A2: 12345 | B2: MG123 | C2: 198.5 | D2: =FLOOR(C2,1) -> 198
A3: 54321 | B3: MG456 | C3: 129.99 | D3: =FLOOR(C3,1) -> 129
A4: 67890 | B4: MG789 | C4: 499 | D4: =FLOOR(C4,1) -> 499
A5: 21098 | B5: MG012 | C5: 99.75 | D5: =FLOOR(C5,1) -> 99

Sheet Analyzing Customer Purchase (Zo
A1: Customer ID | B1: Jan | C1: Feb | D1: Mar | E1: Apr | F1: May | G1: Jun | H1: Jul | I1: Aug | J1: Sep | K1: Oct | L1: Nov | M1: Dec
A2: C001 | B2: 1200 | C2: 1300 | D2: 1250 | E2: 1400 | F2: 1500 | G2: 1450 | H2: 1550 | I2: 1600 | J2: 1650 | K2: 1700 | L2: 1750 | M2: 1800
A3: C002 | B3: 1000 | C3: 1100 | D3: 1050 | E3: 1150 | F3: 1200 | G3: 1250 | H3: 1300 | I3: 1350 | J3: 1400 | K3: 1450 | L3: 1500 | M3: 1550
A4: C003 | B4: 2000 | C4: 2100 | D4: 2050 | E4: 2150 | F4: 2200 | G4: 2250 | H4: 2300 | I4: 2350 | J4: 2400 | K4: 2450 | L4: 2500 | M4: 2550
A5: C004 | B5: 1500 | C5: 1600 | D5: 1550 | E5: 1650 | F5: 1700 | G5: 1750 | H5: 1800 | I5: 1850 | J5: 1900 | K5: 1950 | L5: 2000 | M5: 2050
A6: C005 | B6: 1100 | C6: 1200 | D6: 1150 | E6: 1250 | F6: 1300 | G6: 1350 | H6: 1400 | I6: 1450 | J6: 1500 | K6: 1550 | L6: 1600 | M6: 1650
A7: C006 | B7: 1800 | C7: 1900 | D7: 1850 | E7: 1950 | F7: 2000 | G7: 2050 | H7: 2100 | I7: 2150 | J7: 2200 | K7: 2250 | L7: 2300 | M7: 2350
A8: C007 | B8: 1300 | C8: 1400 | D8: 1350 | E8: 1450 | F8: 1500 | G8: 1550 | H8: 1600 | I8: 1650 | J8: 1700 | K8: 1750 | L8: 1800 | M8: 1850
A9: C008 | B9: 1700 | C9: 1800 | D9: 1750 | E9: 1850 | F9: 1900 | G9: 1950 | H9: 2000 | I9: 2050 | J9: 2100 | K9: 2150 | L9: 2200 | M9: 2250
A10: C009 | B10: 1400 | C10: 1500 | D10: 1450 | E10: 1550 | F10: 1600 | G10: 1650 | H10: 1700 | I10: 1750 | J10: 1800 | K10: 1850 | L10: 1900 | M10: 1950
A11: C010 | B11: 1600 | C11: 1700 | D11: 1650 | E11: 1750 | F11: 1800 | G11: 1850 | H11: 1900 | I11: 1950 | J11: 1950 | K11: 2050 | L11: 2100 | M11: 2150
A13: Standard Deviation | C13: =STDEV(B2:M11) -> 348.99215

Sheet Maximizing Ad Revenue (Google)
A1: Region | B1: Ad Type | C1: Revenue(INR)
A2: North | B2: Display Ads | C2: 1500000
A3: South | B3: Display Ads | C3: 1250000
A4: East | B4: Display Ads | C4: 1800000
A5: West | B5: Display Ads | C5: 1400000
A6: North | B6: Video Ads | C6: 2200000
A7: South | B7: Video Ads | C7: 2450000
A8: East | B8: Video Ads | C8: 2000000
A9: West | B9: Video Ads | C9: 2300000
A10: North | B10: Search Ads | C10: 3000000
A11: South | B11: Search Ads | C11: 2800000
A12: East | B12: Search Ads | C12: 2750000
A13: West | B13: Search Ads | C13: 3100000
A15: Answer | B15: {=INDEX(A2:A13,MATCH(MAX(IF(B2:B13="Display Ads",C2:C13)),C2:C13,0))} -> East | C15: {=INDEX(A2:A13,MATCH(MAX(IF(B2:B13="Video Ads",C2:C13)),C2:C13,0))} -> South
B16: {=INDEX(A2:A13,MATCH(MIN(IF(B2:B13="Display Ads",C2:C13)),C2:C13,0))} -> South | C16: {=INDEX(A2:A13,MATCH(MIN(IF(B2:B13="Video Ads",C2:C13)),C2:C13,0))} -> East

Sheet Randomly Assigning Discount 
A1: Customer Id | B1: Customer Name | C1: Discount Code | E1: Discount Code
A2: C001 | B2: Anil Kumar | C2: =CHOOSE(RANDBETWEEN(1,3),"10%","15%","20%") -> 15% | D2: =RAND() -> 0.82239993 | E2: =IF(D2<=0.33,"10%",IF(D2<=0.66,"15%","20%")) -> 20%
A3: C002 | B3: Priya Sharma | C3: =CHOOSE(RANDBETWEEN(1,3),"10%","15%","20%") -> 15% | D3: =RAND() -> 0.18354363 | E3: =IF(D3<=0.33,"10%",IF(D3<=0.66,"15%","20%")) -> 10%
A4: C003 | B4: Rohit Verma | C4: =CHOOSE(RANDBETWEEN(1,3),"10%","15%","20%") -> 15% | D4: =RAND() -> 0.4261416 | E4: =IF(D4<=0.33,"10%",IF(D4<=0.66,"15%","20%")) -> 15%
A5: C004 | B5: Sunita Rao | C5: =CHOOSE(RANDBETWEEN(1,3),"10%","15%","20%") -> 10% | D5: =RAND() -> 0.54236007 | E5: =IF(D5<=0.33,"10%",IF(D5<=0.66,"15%","20%")) -> 15%
A6: C005 | B6: Rajesh Singh | C6: =CHOOSE(RANDBETWEEN(1,3),"10%","15%","20%") -> 20% | D6: =RAND() -> 0.95710414 | E6: =IF(D6<=0.33,"10%",IF(D6<=0.66,"15%","20%")) -> 20%
A7: C006 | B7: Neha Gupta | C7: =CHOOSE(RANDBETWEEN(1,3),"10%","15%","20%") -> 15% | D7: =RAND() -> 0.57254336 | E7: =IF(D7<=0.33,"10%",IF(D7<=0.66,"15%","20%")) -> 15%
A8: C007 | B8: Manish Tiwari | C8: =CHOOSE(RANDBETWEEN(1,3),"10%","15%","20%") -> 15% | D8: =RAND() -> 0.43587734 | E8: =IF(D8<=0.33,"10%",IF(D8<=0.66,"15%","20%")) -> 15%
A9: C008 | B9: Kavita Patel | C9: =CHOOSE(RANDBETWEEN(1,3),"10%","15%","20%") -> 20% | D9: =RAND() -> 0.45937704 | E9: =IF(D9<=0.33,"10%",IF(D9<=0.66,"15%","20%")) -> 15%
A10: C009 | B10: Rakesh Mehra | C10: =CHOOSE(RANDBETWEEN(1,3),"10%","15%","20%") -> 15% | D10: =RAND() -> 0.26712928 | E10: =IF(D10<=0.33,"10%",IF(D10<=0.66,"15%","20%")) -> 10%
A11: C010 | B11: Pooja Joshi | C11: =CHOOSE(RANDBETWEEN(1,3),"10%","15%","20%") -> 10% | D11: =RAND() -> 0.54987349 | E11: =IF(D11<=0.33,"10%",IF(D11<=0.66,"15%","20%")) -> 15%

Sheet Identifying Income Batch Codes
A1: Batch Code | B1: Product Name | C1: Is Batch Code Valid
A2: SHMP-001234 | B2: SunSilk Smooth & Shiny Shampoo | C2: =IF(LEN(A2)=11,"Valid Code","Invalid Code") -> Valid Code | D2: =IFERROR(LEN(A2)<>11,"Invalid Code") -> FALSE
A3: SHMP-AB12345 | B3: Dove Nourishing Oil Care Shampoo | C3: =IF(LEN(A3)=11,"Valid Code","Invalid Code") -> Invalid Code | D3: =IFERROR(LEN(A3)<>11,"Invalid Code") -> TRUE
A4: SHMP-XY9999 | B4: Head & Shoulders Cool Menthol Shampoo | C4: =IF(LEN(A4)=11,"Valid Code","Invalid Code") -> Valid Code | D4: =IFERROR(LEN(A4)<>11,"Invalid Code") -> FALSE
A5: SHMP-123AA | B5: SunSilk Smooth Shampoo | C5: =IF(LEN(A5)=11,"Valid Code","Invalid Code") -> Invalid Code | D5: =IFERROR(LEN(A5)<>11,"Invalid Code") -> TRUE
A6: SHMP-123456789A | B6: Dove Basic Oil Care Shampoo | C6: =IF(LEN(A6)=11,"Valid Code","Invalid Code") -> Invalid Code | D6: =IFERROR(LEN(A6)<>11,"Invalid Code") -> TRUE
A7: SHMP-YYZZ1234 | B7: Head & Shoulders Quick Dry Shampoo | C7: =IF(LEN(A7)=11,"Valid Code","Invalid Code") -> Invalid Code | D7: =IFERROR(LEN(A7)<>11,"Invalid Code") -> TRUE

Sheet Analyzing Client Investment
A1: Client Investment Data
A2: Client ID | B2: Asset Type | C2: Investment Amount
A3: 1001 | B3: Stocks | C3: 50000
A4: 1001 | B4: Bonds | C4: 20000
A5: 1001 | B5: Real Estate | C5: 30000
A6: 1002 | B6: Stocks | C6: 70000
A7: 1002 | B7: Bonds | C7: 40000
A8: 1002 | B8: Mutual Funds | C8: 25000
A9: 1003 | B9: Real Estate | C9: 60000
A10: 1003 | B10: Stocks | C10: 50000
A11: 1003 | B11: Bonds | C11: 35000
A13: Client Summary
A14: Client Id | B14: Stocks | C14: Bonds | D14: Real Estate | E14: Mutual Funds | F14: Total Investment
A15: 1001 | B15: {=INDEX(C2:C11, MATCH(1, (A2:A11=A15)*(B2:B11=B14), 0))} -> 50000 | C15: {=INDEX(C2:C11, MATCH(1, (A2:A11=A15)*(B2:B11=C14), 0))} -> 20000 | D15: {=INDEX(C2:C11, MATCH(1, (A2:A11=A15)*(B2:B11=D14), 0))} -> 30000 | E15: {=INDEX(C2:C11, MATCH(1, (A2:A11=A15)*(B2:B11=E14), 0))} -> #N/A
A16: 1002 | B16: {=INDEX(C2:C11, MATCH(1, (A2:A11=A16)*(B2:B11=B14), 0))} -> 70000 | C16: {=INDEX(C2:C11, MATCH(1, (A2:A11=A16)*(B2:B11=C14), 0))} -> 40000 | D16: {=INDEX(C2:C11, MATCH(1, (A2:A11=A16)*(B2:B11=D14), 0))} -> #N/A | E16: {=INDEX(C2:C11, MATCH(1, (A2:A11=A16)*(B2:B11=E14), 0))} -> 25000
A17: 1003 | B17: {=INDEX(C2:C12, MATCH(1, (A2:A12=A17)*(B2:B12=B14), 0))} -> 50000 | C17: {=INDEX(C2:C11, MATCH(1, (A2:A11=A17)*(B2:B11=C14), 0))} -> 35000 | D17: {=INDEX(C2:C11, MATCH(1, (A2:A11=A17)*(B2:B11=D14), 0))} -> 60000 | E17: {=INDEX(C2:C12, MATCH(1, (A2:A12=A17)*(B3:B12=E14), 0))} -> #N/A
A19: Client Investment Calculator
A20: Client Id | B20: Asset Type | C20: Investment Amount
A21: 1003 | B21: Bonds | C21: =VLOOKUP(A21,A2:C11,3) -> 35000

Sheet Email Normalization 
A1: Email Address | B1: Normalized Email
A2: john.doe@gmail.com | B2: =SUBSTITUTE(LEFT(A2,FIND("@",A2)-1),".","") & MID(A2,FIND("@",A2),LEN(A2)) -> johndoe@gmail.com
A3: jane.smith@gmail.com | B3: =SUBSTITUTE(LEFT(A3,FIND("@",A3)-1),".","")& MID(A3,FIND("@",A3),LEN(A3)) -> janesmith@gmail.com
A4: j.ohndoe@gmail.com | B4: =SUBSTITUTE(LEFT(A4,FIND("@",A4)-1),".","")& MID(A4,FIND("@",A4),LEN(A4)) -> johndoe@gmail.com
A5: jan.e.sm.ith@gmail.com | B5: =SUBSTITUTE(LEFT(A5,FIND("@",A5)-1),".","")& MID(A5,FIND("@",A5),LEN(A5)) -> janesmith@gmail.com
A6: mark.parker@yahoo.com | B6: =SUBSTITUTE(LEFT(A6,FIND("@",A6)-1),".","")& MID(A6,FIND("@",A6),LEN(A6)) -> markparker@yahoo.com

Sheet Loan Disbursement Analysis
A1: Loan ID | B1: Loan Type | C1: Loan Amount
A2: 1001 | B2: Personal | C2: 500000
A3: 1002 | B3: Business | C3: 1200000
A4: 1003 | B4: Personal | C4: 700000
A5: 1004 | B5: Business | C5: 2000000
A6: 1005 | B6: Education | C6: 300000
A7: 1006 | B7: Personal | C7: 450000
A8: 1007 | B8: Business | C8: 1500000
A9: 1008 | B9: Education | C9: 200000
A10: 1009 | B10: Personal | C10: 600000
A11: 1010 | B11: Business | C11: 1800000
A12: 1011 | B12: Education | C12: 400000
A13: 1012 | B13: Personal | C13: 550000
... A16: 1015 | B16: Business | C16: 1900000
A18: Total Amount Disbursed for Personal Loans | E18: =SUMIF(B2:B16,"Personal",C2:C16) -> 3550000
A19: Total Amount Disbursed for Business Loans | E19: =SUMIF(B2:B16,"Personal",C2:C16) -> 3550000
A20: Total Amount Disbursed for Education Loans | E20: =SUMIF(B2:B16,"Education",C2:C16) -> 900000

Sheet Branch Allocation
A1: Number | B1: Account Age(Months) | C1: Branch Allocation
A2: 1234567890 | B2: 8 | C2: =MOD(B2,3)+1 -> 3
A3: 9876543210 | B3: 22 | C3: =MOD(B3,3)+1 -> 2
A4: 123456789 | B4: 36 | C4: =MOD(B4,3)+1 -> 1

Sheet Analyzing Monthly Sales
A1: Sale Id | B1: Sale Date | C1: Sale Amount | D1: Month
A2: 1 | B2: 44927 | C2: 50000 | D2: =MONTH(B2) -> 1
A3: 2 | B3: 44941 | C3: 75000 | D3: =MONTH(B3) -> 1
A4: 3 | B4: 44959 | C4: 60000 | D4: =MONTH(B4) -> 2
A5: 4 | B5: 44975 | C5: 85000 | D5: =MONTH(B5) -> 2
A6: 5 | B6: 44990 | C6: 40000 | D6: =MONTH(B6) -> 3
A7: 6 | B7: 45006 | C7: 95000 | D7: =MONTH(B7) -> 3

Sheet Assessing Sales and Advertising
A1: Month | B1: Advertising Spend (INR lakhs) | C1: Sales Revenue(INR Crores)
A2: January | B2: 50 | C2: 1.2
A3: February | B3: 55 | C3: 1.4
A4: March | B4: 60 | C4: 1.5
A5: April | B5: 65 | C5: 1.6
A6: May | B6: 70 | C6: 1.8
A7: June | B7: 75 | C7: 1.9
A8: July | B8: 80 | C8: 2
A9: August | B9: 85 | C9: 2.2
A10: September | B10: 90 | C10: 2.3
A11: October | B11: 95 | C11: 2.5
A12: November | B12: 100 | C12: 2.6
A13: December | B13: 105 | C13: 2.8
A15: Covariance | B15: =+COVAR(B2:B13,C2:C13) -> 8.375
A16: Correlation | B16: =CORREL(B2:B13,C2:C13) -> 0.99798471

Sheet Analyzing Median Delivery Time 
A1: Transaction ID | B1: Delivery Time (Days)
A2: T001 | B2: 3
A3: T002 | B3: 5
A4: T003 | B4: 2
A5: T004 | B5: 4
A6: T005 | B6: 6
A7: T006 | B7: 7
A8: T007 | B8: 5
A9: T008 | B9: 3
A10: T009 | B10: 4
A11: T010 | B11: 2
A14: Median | B14: =MEDIAN(B2:B11) -> 4
A15: Average | B15: =AVERAGE(B2:B11) -> 4.1

Sheet Calculating Total Cost and Disc
A1: Item | B1: Qty | C1: Unit Price | D1: Total Cost | E1: Discount Applied | F1: Final Cost
A2: Sofa Set | B2: 1 | C2: 30000 | D2: =B2*C2 -> 30000 | E2: =0.07*D2 -> 2100 | F2: =D2-E2 -> 27900
A3: Dinning Table | B3: 2 | C3: 15000 | D3: =B3*C3 -> 30000 | E3: =0.07*D3 -> 2100 | F3: =D3-E3 -> 27900
A4: Bed Frame | B4: 1 | C4: 25000 | D4: =B4*C4 -> 25000 | E4: =0.05*D4 -> 1250 | F4: =D4-E4 -> 23750

Sheet Analyzing Student Performance 
A1: Student Id | B1: Grade | C1: Test Score
A2: VED101 | B2: 6th | C2: 85
A3: VED102 | B3: 7th | C3: 78
A4: VED103 | B4: 6th | C4: 92
A5: VED104 | B5: 7th | C5: 69
A6: VED105 | B6: 7th | C6: 87
A8: Grade | B8: Average Score
A9: 6th | B9: =IF(A9="6th",AVERAGE(C2:C6),) -> 82.2
A10: 7th | B10: =IF(A10="7th",AVERAGE(C2:C7),) -> 82.2

Sheet Tracking Monthly Revenue
A1: Month | B1: Mumbai | C1: Delhi | D1: Bengaluru | E1: Hyderabad | F1: Chennai
A2: January | B2: 50000 | C2: 45000 | D2: 40000 | E2: 35000 | F2: 30000
A3: February | B3: 52000 | C3: 47000 | D3: 42000 | E3: 37000 | F3: 32000
A4: March | B4: 53000 | C4: 48000 | D4: 43000 | E4: 38000 | F4: 33000
A5: April | B5: 54000 | C5: 49000 | D5: 44000 | E5: 39000 | F5: 34000
A6: May | B6: 55000 | C6: 50000 | D6: 45000 | E6: 40000 | F6: 35000
A7: June | B7: 56000 | C7: 51000 | D7: 46000 | E7: 41000 | F7: 36000
A9: Data for | B9: Mumbai | C9: for | D9: March | E9: =VLOOKUP(D9,A1:F7,2) -> 53000 | F9: =VLOOKUP(B9,A1:F7,MATCH(D9,A2:A7,0),FALSE) -> #N/A
A10: Data for | B10: Bengaluru | C10: for | D10: April | E10: =VLOOKUP(D10,A1:F7,2) -> #N/A

Sheet Tracking Delivery Times
A1: Order Id | B1: Order Date & time | C1: Delivery Date & time | D1: Time taken(In hours)
A2: 1 | B2: 45572.417 | C2: 45572.521 | D2: =(C2-B2)*24 -> 2.5
A3: 2 | B3: 45572.479 | C3: 45572.583 | D3: =(C3-B3)*24 -> 2.5
A4: 3 | B4: 45572.542 | C4: 45572.656 | D4: =(C4-B4)*24 -> 2.75
A5: 4 | B5: 45572.625 | C5: 45572.719 | D5: =(C5-B5)*24 -> 2.25
A6: 5 | B6: 45572.729 | C6: 45572.781 | D6: =(C6-B6)*24 -> 1.25
A8: Average Delivery Time | B8: =AVERAGE(D2:D6) -> 2.25
A9: Date and time of last delivery | B9: =LARGE(C2:C6,1) -> 45572.781

Sheet Encoding Course Categories
A1: Course Category | B1: ASCII Code | C1: Character
A2: UPSC | B2: 85 | C2: =CHAR(B2) -> U
A3: NEET | B3: 78 | C3: =CHAR(B3) -> N
A4: JEE | B4: 74 | C4: =CHAR(B4) -> J
A5: CAT | B5: 67 | C5: =CHAR(B5) -> C
A6: GATE | B6: 71 | C6: =CHAR(B6) -> G

Sheet Calculating Total Revenue 
A1: Month | B1: Revenue in $MM
A2: Janaury | B2: 820
A3: February | B3: 215
A4: March | B4: 60
A5: April | B5: 470
A6: May | B6: 210
A7: June | B7: 75
A8: July | B8: 750
A9: August | B9: 490
A10: September | B10: 630
A11: October | B11: 260
A12: November | B12: 720
A13: December | B13: 210
A15: Total Year | B15: =SUM(B2:B13) -> 4910

Sheet Rounding Down Monthly
A1: Product | B1: Monthly Revenue | C1: Rounded Down Monthly Revenue
A2: Freshdesk | B2: 15432 | C2: =ROUNDDOWN(B2,-3) -> 15000
A3: Freshservice | B3: 29756 | C3: =ROUNDDOWN(B3,-3) -> 29000
A4: Freshsales | B4: 8345 | C4: =ROUNDDOWN(B4,-3) -> 8000
A5: Freshmarketer | B5: 45321 | C5: =ROUNDDOWN(B5,-3) -> 45000
A6: Freshteam | B6: 12367 | C6: =ROUNDDOWN(B6,-3) -> 12000
A7: Freshchat | B7: 23154 | C7: =ROUNDDOWN(B7,-3) -> 23000
A8: Freshcaller | B8: 18732 | C8: =ROUNDDOWN(B8,-3) -> 18000
A9: Freshping | B9: 6543 | C9: =ROUNDDOWN(B9,-3) -> 6000
A10: Freshstatus | B10: 34987 | C10: =ROUNDDOWN(B10,-3) -> 34000
A11: Freshrelease | B11: 9812 | C11: =ROUNDDOWN(B11,-3) -> 9000

Sheet Analyzing Volunteer Engagement
A1: Region | B1: Volunteering Hours
A2: North | B2: 15
A3: North | B3: 20
A4: North | B4: 18
A5: North | B5: 22
A6: South | B6: 25
A7: South | B7: 30
A8: South | B8: 28
A9: South | B9: 32
A10: East | B10: 10
A11: East | B11: 12
A12: East | B12: 14
A13: East | B13: 16
... A17: West | B17: 26
A19: Answer | B19: =_xlfn.STDEV.P(B2:B17) -> 6.2537489

Sheet Vehicle Age Classification
A1: Vehicle ID | B1: Vehicle Model | C1: Manufacturing Year | D1: Age Classification
A2: 1001 | B2: Maruti Swift | C2: 2023 | D2: =IF(C2>=2022,"New", IF(AND(C2>=2018,C2<=2021),"Moderate", IF(AND(C2>=2015,C2<=2017),"Old", IF(C2<=2014,"Very Old","") ))) -> New
A3: 1002 | B3: Hyundai i20 | C3: 2020 | D3: =IF(C3>=2022,"New", IF(AND(C3>=2018,C3<=2021),"Moderate", IF(AND(C3>=2015,C3<=2017),"Old", IF(C3<=2014,"Very Old","") ))) -> Moderate
A4: 1003 | B4: Honda City | C4: 2017 | D4: =IF(C4>=2022,"New", IF(AND(C4>=2018,C4<=2021),"Moderate", IF(AND(C4>=2015,C4<=2017),"Old", IF(C4<=2014,"Very Old","") ))) -> Old
A5: 1004 | B5: Toyota Fortuner | C5: 2015 | D5: =IF(C5>=2022,"New", IF(AND(C5>=2018,C5<=2021),"Moderate", IF(AND(C5>=2015,C5<=2017),"Old", IF(C5<=2014,"Very Old","") ))) -> Old
A6: 1005 | B6: Tata Nexon | C6: 2019 | D6: =IF(C6>=2022,"New", IF(AND(C6>=2018,C6<=2021),"Moderate", IF(AND(C6>=2015,C6<=2017),"Old", IF(C6<=2014,"Very Old","") ))) -> Moderate
A7: 1006 | B7: Ford EcoSport | C7: 2014 | D7: =IF(C7>=2022,"New", IF(AND(C7>=2018,C7<=2021),"Moderate", IF(AND(C7>=2015,C7<=2017),"Old", IF(C7<=2014,"Very Old","") ))) -> Very Old
A8: 1007 | B8: Kia Seltos | C8: 2022 | D8: =IF(C8>=2022,"New", IF(AND(C8>=2018,C8<=2021),"Moderate", IF(AND(C8>=2015,C8<=2017),"Old", IF(C8<=2014,"Very Old","") ))) -> New
A9: 1008 | B9: Mahindra Scorpio | C9: 2016 | D9: =IF(C9>=2022,"New", IF(AND(C9>=2018,C9<=2021),"Moderate", IF(AND(C9>=2015,C9<=2017),"Old", IF(C9<=2014,"Very Old","") ))) -> Old
A10: 1009 | B10: Volkswagen Polo | C10: 2013 | D10: =IF(C10>=2022,"New", IF(AND(C10>=2018,C10<=2021),"Moderate", IF(AND(C10>=2015,C10<=2017),"Old", IF(C10<=2014,"Very Old","") ))) -> Very Old
A11: 1010 | B11: Renault Kwid | C11: 2021 | D11: =IF(C11>=2022,"New", IF(AND(C11>=2018,C11<=2021),"Moderate", IF(AND(C11>=2015,C11<=2017),"Old", IF(C11<=2014,"Very Old","") ))) -> Moderate

Sheet Advanced Inventory Analysis
A1: Product Id | B1: Product Name | C1: Category | D1: Stock Quantity | E1: Price per Unit | F1: Supplier
A2: 101 | B2: Basmati Rice | C2: Grains | D2: 150 | E2: 60 | F2: Supplier A
A3: 102 | B3: Wheat flour | C3: Grains | D3: 200 | E3: 40 | F3: Supplier B
A4: 103 | B4: Turmeric Powder | C4: Spices | D4: 80 | E4: 120 | F4: Supplier A
A5: 104 | B5: Red Chilli Powder | C5: Spices | D5: 100 | E5: 150 | F5: Supplier C
A6: 105 | B6: Sunflower oil | C6: Oils | D6: 50 | E6: 130 | F6: Supplier B
A7: 106 | B7: Mustard Oil | C7: Oils | D7: 75 | E7: 110 | F7: Supplier A
A8: 107 | B8: Sugar | C8: Sweetners | D8: 250 | E8: 45 | F8: Supplier C
A9: 108 | B9: Salt | C9: Condiments | D9: 300 | E9: 20 | F9: Supplier B
A10: 109 | B10: Honey | C10: Sweetners | D10: 60 | E10: 180 | F10: Supplier A
A11: 110 | B11: Green Tea | C11: Beverages | D11: 90 | E11: 250 | F11: Supplier C
B14: Stock Quantity of: | C14: Mustard Oil | D14: =VLOOKUP(C14,B1:F11,3,FALSE) -> 75
B15: Total Value of Stock for | C15: Supplier A | D15: =SUMPRODUCT((F2:F11=C15)*D2:D11*E2:E11) -> 37650
C16: Supplier B | D16: =SUMPRODUCT((F2:F11=C16)*D2:D11*E2:E11) -> 20500
C17: Supplier C | D17: =SUMPRODUCT((F2:F11=C17)*D2:D11*E2:E11) -> 48750

Sheet Lead Conversion Calculator
A1: Campaign | B1: January | C1: February | D1: March | E1: April | F1: May | G1: June
A2: Campaign A | B2: 0.05 | C2: 0.07 | D2: 0.06 | E2: 0.08 | F2: 0.075 | G2: 0.09
A3: Campaign B | B3: 0.045 | C3: 0.06 | D3: 0.07 | E3: 0.085 | F3: 0.068 | G3: 0.1
A4: Campaign C | B4: 0.06 | C4: 0.072 | D4: 0.065 | E4: 0.09 | F4: 0.083 | G4: 0.095
A5: Campaign D | B5: 0.055 | C5: 0.065 | D5: 0.073 | E5: 0.088 | F5: 0.077 | G5: 0.102
A8: Conversion Rate Calculator | D8: Campaign A | E8: March | F8: =VLOOKUP(D8,A1:G5,4) -> 0.06
D9: Campaign B | E9: April | F9: =VLOOKUP(D9,A1:G5,3) -> 0.06
D10: Campaign C | E10: May | F10: =VLOOKUP(D10,A1:G5,6) -> 0.083
D11: Campaign A | E11: January | F11: =VLOOKUP(D11,A1:G5,2) -> 0.05
D12: Campaign B | E12: February | F12: =VLOOKUP(D12,A1:G5,3) -> 0.06

Sheet Average Mango Prices
A1: State | B1: Price per kg
A2: Maharashtra | B2: 85
A3: Andhra Pradesh | B3: 72
A4: Karnataka | B4: 90
A5: Gujarat | B5: 80
A7: Answer | B7: =AVERAGE(B2:B5) -> 81.75

Sheet Analyzing Customer Support Tkt
A1: Ticket id | B1: Raw Ticket Data | C1: Customer Full Name | D1: Ticket Number | E1: Issue Description
A2: T001 | B2: John,Doe[#12345]-Internet is down since last night | C2: =SUBSTITUTE(LEFT(B2,FIND("[#",B2)-1),","," ") -> John Doe | D2: =MID(B2,FIND("[#",B2)+2,FIND("]",B2)-FIND("[#",B2)-2) -> 12345 | E2: =MID(B2, FIND("]-", B2) + 2, LEN(B2)) -> Internet is down since last night | F2: =FIND("-", B2) -> 17
A3: T002 | B3: Mary,Jane[#23456]-Billing Issue: charged twice for the same month | C3: =SUBSTITUTE(LEFT(B3,FIND("[#",B3)-1),","," ") -> Mary Jane | D3: =MID(B3,FIND("[#",B3)+2,FIND("]",B3)-FIND("[#",B3)-2) -> 23456 | E3: =MID(B3,FIND("]-",B3)+2,LEN(B3)) -> Billing Issue: charged twice for the same month
A4: T003 | B4: Ahmed,Khan [#34567]- Need assistance with setting up a new router | C4: =SUBSTITUTE(LEFT(B4,FIND("[#",B4)-1),","," ") -> Ahmed Khan | D4: =MID(B4,FIND("[#",B4)+2,FIND("]",B4)-FIND("[#",B4)-2) -> 34567 | E4: =MID(B4,FIND("]-",B4)+2,LEN(B4)) -> Need assistance with setting up a new router
A5: T004 | B5: Priya, Sharma [#45678]-The network coverage is poor in my area | C5: =SUBSTITUTE(LEFT(B5,FIND("[#",B5)-1),","," ") -> Priya Sharma | D5: =MID(B5,FIND("[#",B5)+2,FIND("]",B5)-FIND("[#",B5)-2) -> 45678 | E5: =MID(B5,FIND("]-",B5)+2,LEN(B5)) -> The network coverage is poor in my area
A6: T005 | B6: Rajesh,Gupta [#56789]- Connection speed is very slow,experiencing frequent disconnections | C6: =SUBSTITUTE(LEFT(B6,FIND("[#",B6)-1),","," ") -> Rajesh Gupta | D6: =MID(B6,FIND("[#",B6)+2,FIND("]",B6)-FIND("[#",B6)-2) -> 56789 | E6: =MID(B6,FIND("]-",B6)+2,LEN(B6)) -> Connection speed is very slow,experiencing frequent disconnections

Sheet Customer Loan Details Analysis
A1: Customer Id | B1: Raw Loan Data | C1: Customer Name | D1: Loan Amount | E1: Interest Rate | F1: Tenure | G1: Status | H1: Total Interest | I1: Approval Status | J1: Approved and Above Avg
A2: C001 | B2: ramesh kumar,Loan Amount:500000,Interest Rate:7.5%Tenure:10 Years,Approved | C2: =PROPER(LEFT(B2, FIND(",", B2)-1)) -> Ramesh Kumar | D2: =MID(B2, FIND("Loan Amount:", B2)+12, FIND(",", B2, FIND("Loan Amount:", B2)) - (FIND("Loan Amount:", B2)+12)) -> 500000 | E2: =VALUE(SUBSTITUTE(MID(B2, FIND("Interest Rate:",B2)+14, FIND("Tenure:",B2)- (FIND("Interest Rate:",B2)+14)),"%","")) -> 7.5 | F2: =MID(B2, FIND("Tenure:",B2)+7, FIND(",",B2,FIND("Tenure:",B2))- (FIND("Tenure:",B2)+12)) -> 10 | H2: =D2*E2*F2/100 -> 375000
A3: C002 | B3: Rita Gupta,Loan Amount:300000,Interest Rate:8.2%Tenure:7 Years,Rejected | C3: =PROPER(LEFT(B3,FIND(",",B3)-1)) -> Rita Gupta | D3: =MID(B3, FIND("Loan Amount:", B3)+12, FIND(",", B3, FIND("Loan Amount:", B3)) - (FIND("Loan Amount:", B3)+12)) -> 300000 | E3: =VALUE(SUBSTITUTE(MID(B3, FIND("Interest Rate:",B3)+14, FIND("Tenure:",B3)- (FIND("Interest Rate:",B3)+14)),"%","")) -> 8.2 | F3: =MID(B3, FIND("Tenure:",B3)+7, FIND(",",B3,FIND("Tenure:",B3))- (FIND("Tenure:",B3)+12)) -> 7 | H3: =D3*E3*F3/100 -> 172200
A4: C003 | B4: Vijay singh,Loan Amount:1000000,Interest Rate:6.9%Tenure:15 Years,Approved | C4: =PROPER(LEFT(B4,FIND(",",B4)-1)) -> Vijay Singh | D4: =MID(B4, FIND("Loan Amount:", B4)+12, FIND(",", B4, FIND("Loan Amount:", B4)) - (FIND("Loan Amount:", B4)+12)) -> 1000000 | E4: =VALUE(SUBSTITUTE(MID(B4, FIND("Interest Rate:",B4)+14, FIND("Tenure:",B4)- (FIND("Interest Rate:",B4)+14)),"%","")) -> 6.9 | F4: =MID(B4, FIND("Tenure:",B4)+7, FIND(",",B4,FIND("Tenure:",B4))- (FIND("Tenure:",B4)+12)) -> 15 | H4: =D4*E4*F4/100 -> 1035000
A5: C004 | B5: priya Iyer,Loan Amount:250000,Interest Rate:7.8%Tenure:5 Years,Approved | C5: =PROPER(LEFT(B5,FIND(",",B5)-1)) -> Priya Iyer | D5: =MID(B5, FIND("Loan Amount:", B5)+12, FIND(",", B5, FIND("Loan Amount:", B5)) - (FIND("Loan Amount:", B5)+12)) -> 250000 | E5: =VALUE(SUBSTITUTE(MID(B5, FIND("Interest Rate:",B5)+14, FIND("Tenure:",B5)- (FIND("Interest Rate:",B5)+14)),"%","")) -> 7.8 | F5: =MID(B5, FIND("Tenure:",B5)+7, FIND(",",B5,FIND("Tenure:",B5))- (FIND("Tenure:",B5)+12)) -> 5 | H5: =D5*E5*F5/100 -> 97500
A6: C005 | B6: Anil Kumar,Loan Amount:750000,Interest Rate:8.0%Tenure:12 Years,Approved | C6: =PROPER(LEFT(B6,FIND(",",B6)-1)) -> Anil Kumar | D6: =MID(B6, FIND("Loan Amount:", B6)+12, FIND(",", B6, FIND("Loan Amount:", B6)) - (FIND("Loan Amount:", B6)+12)) -> 750000 | E6: =VALUE(SUBSTITUTE(MID(B6, FIND("Interest Rate:",B6)+14, FIND("Tenure:",B6)- (FIND("Interest Rate:",B6)+14)),"%","")) -> 8 | F6: =MID(B6, FIND("Tenure:",B6)+7, FIND(",",B6,FIND("Tenure:",B6))- (FIND("Tenure:",B6)+12)) -> 12 | H6: =D6*E6*F6/100 -> 720000

Sheet Targeting Mobile App Users
A1: User Id | B1: City Tier | C1: Average Daily App Usage (In Minutes) | D1: Meets Condition
A2: USR123 | B2: Tier 1 | C2: 45 | D2: =IF(AND(B2="Tier 1",C2>30),TRUE,FALSE) -> TRUE
A3: USR456 | B3: Tier 2 | C3: 20 | D3: =IF(AND(B3="Tier 1",C3>30),TRUE,FALSE) -> FALSE
A4: USR789 | B4: Tier 1 | C4: 10 | D4: =IF(AND(B4="Tier 1",C4>30),TRUE,FALSE) -> FALSE
A5: USR012 | B5: Tier 3 | C5: 60 | D5: =IF(AND(B5="Tier 1",C5>30),TRUE,FALSE) -> FALSE

Sheet Standardizing Seller
A1: Seller Id | B1: Seller Name | C1: Joining Month | D1: Standardizing Seller Name | E1: Standardizing Month Name
A2: 101 | B2: Ram Trdaing Co. | C2: January | D2: =LOWER(B2) -> ram trdaing co. | E2: =LOWER(C2) -> january
A3: 102 | B3: MAHESH Enterprises | C3: February | D3: =LOWER(B3) -> mahesh enterprises | E3: =LOWER(C3) -> february
A4: 103 | B4: Vinayaka STORES | C4: March | D4: =LOWER(B4) -> vinayaka stores | E4: =LOWER(C4) -> march
A5: 104 | B5: Anand & Sons | C5: April | D5: =LOWER(B5) -> anand & sons | E5: =LOWER(C5) -> april
A6: 105 | B6: SHREE GANESH Mart | C6: May | D6: =LOWER(B6) -> shree ganesh mart | E6: =LOWER(C6) -> may

Sheet Optimizing Delivery Capacity 
A1: Area | B1: Friday Evening | C1: Saturday Daytime | D1: Saturday Eveninh | E1: Sunday Daytime | F1: Sunday Evening | G1: Highest Ride Request
A2: South Mumbai | B2: 250 | C2: 180 | D2: 320 | E2: 150 | F2: 200 | G2: =LARGE(B2:F2,1) -> 320
A3: Bandra-Kurla Complex | B3: 120 | C3: 210 | D3: 180 | E3: 140 | F3: 160 | G3: =LARGE(B3:F3,1) -> 210
A4: Andheri West | B4: 300 | C4: 250 | D4: 350 | E4: 220 | F4: 280 | G4: =LARGE(B4:F4,1) -> 350
A5: Powai | B5: 180 | C5: 150 | D5: 200 | E5: 120 | F5: 130 | G5: =LARGE(B5:F5,1) -> 200

Sheet Analyzing Ad Engagement
A1: Ad ID | B1: Ad Type | C1: Impressions | D1: Clicks | E1: Has Zero Clicks
A2: A001 | B2: Banner Ad | C2: 5000 | D2: 120 | E2: =IF(D2=0,TRUE,FALSE) -> FALSE
A3: A002 | B3: Video Ad | C3: 3000 | D3: 0 | E3: =IF(D3=0,TRUE,FALSE) -> TRUE
A4: A003 | B4: Carousel Ad | C4: 4500 | D4: 80 | E4: =IF(D4=0,TRUE,FALSE) -> FALSE
A5: A004 | B5: Sponsored Post | C5: 6000 | D5: 150 | E5: =IF(D5=0,TRUE,FALSE) -> FALSE
A6: A005 | B6: Display Ad | C6: 2500 | D6: 0 | E6: =IF(D6=0,TRUE,FALSE) -> TRUE
A7: A006 | B7: Native Ad | C7: 4000 | D7: 60 | E7: =IF(D7=0,TRUE,FALSE) -> FALSE
A8: A007 | B8: Text Ad | C8: 3500 | D8: 90 | E8: =IF(D8=0,TRUE,FALSE) -> FALSE
A9: A008 | B9: Pop-up Ad | C9: 2000 | D9: 0 | E9: =IF(D9=0,TRUE,FALSE) -> TRUE
A10: A009 | B10: Overlay Ad | C10: 2800 | D10: 70 | E10: =IF(D10=0,TRUE,FALSE) -> FALSE
A11: A010 | B11: Interactive Ad | C11: 5000 | D11: 110 | E11: =IF(D11=0,TRUE,FALSE) -> FALSE
A13: Answer | B13: =COUNTIF(E2:E11,TRUE) -> 3

Sheet Matching Customer Engagement
A1: Service Name | B1: Engagement Rate (%)
A2: SMS Marketing | B2: 45
A3: Chatbots | B3: 62
A4: Voice Messaging | B4: 53
A5: Email Integration | B5: 37
A6: Push Notifications | B6: 58
A8: Chatbots | B8: =VLOOKUP(A8,A1:B6,2,FALSE) -> 62

Sheet Analyzing Cricket Contest Data
A1: Month | B1: Contest A | C1: Contest B | D1: Contest C | E1: Contest D | F1: Contest E
A2: January | B2: 150000 | C2: 200000 | D2: 175000 | E2: 220000 | F2: 180000
A3: February | B3: 160000 | C3: 210000 | D3: 185000 | E3: 230000 | F3: 190000
A4: March | B4: 170000 | C4: 220000 | D4: 195000 | E4: 240000 | F4: 200000
A5: April | B5: 180000 | C5: 230000 | D5: 205000 | E5: 250000 | F5: 210000
A6: May | B6: 190000 | C6: 240000 | D6: 215000 | E6: 260000 | F6: 220000
A7: June | B7: 200000 | C7: 250000 | D7: 225000 | E7: 270000 | F7: 230000
A9: Contest Name | B9: Target Month | C9: Prize Money
A10: Contest B | B10: March | C10: =VLOOKUP(B10,A1:F7,3,FALSE) -> 220000
A11: Contest C | B11: February | C11: =VLOOKUP(B11,A1:F7,4,FALSE) -> 185000
A12: Contest E | B12: June | C12: =VLOOKUP(B12,A2:F7,6,FALSE) -> 230000

Sheet Daily Cash Deposit Analysis
A1: Day | B1: Total Cash Deposited
A2: Monday | B2: 254872
A3: Tuesday | B3: 189541
A4: Wednesday | B4: 321457
A5: Thursday | B5: 217890
A6: Friday | B6: 482569
A7: Saturday | B7: 314872
A8: Sunday | B8: 152489
A10: Answer | B10: =COUNTIF(B2:B8, ">=" & AVERAGE(B2:B8)) -> 3
B11: =COUNTIF(B2:B8,"<" & AVERAGE(B2:B8)) -> 4

Sheet Ranking Car Models
A1: Car Model | B1: Units Sold Q1 2024 | C1: Rank
A2: Maruti Swift | B2: 150 | C2: =RANK($B$2:$B$6,$B$2:$B$6,0) -> 1
A3: Tata Nexon | B3: 90 | C3: =RANK($B$2:$B$6,$B$2:$B$6,0) -> 3
A4: Hyundai i20 | B4: 120 | C4: =RANK($B$2:$B$6,$B$2:$B$6,0) -> 2
A5: Mahindra XUV500 | B5: 70 | C5: =RANK($B$2:$B$6,$B$2:$B$6,0) -> 5
A6: Honda City | B6: 80 | C6: =RANK($B$2:$B$6,$B$2:$B$6,0) -> 4

Sheet Booking Analysis for Oberoi
A1: Booking ID | B1: Customer Name | C1: Check In Date | D1: Check Out Date | E1: Year | F1: Stay Duration
A2: 1 | B2: John Doe | C2: 44923 | D2: 44928 | E2: =YEAR(C2) -> 2022 | F2: =_xlfn.DAYS(D2,C2) -> 5
A3: 2 | B3: Jane Smith | C3: 45000 | D3: 45003 | E3: =YEAR(C3) -> 2023 | F3: =_xlfn.DAYS(D3,C3) -> 3
A4: 3 | B4: Miachel Brown | C4: 45066 | D4: 45071 | E4: =YEAR(C4) -> 2023 | F4: =_xlfn.DAYS(D4,C4) -> 5
A5: 4 | B5: Sarah Johnson | C5: 45117 | D5: 45122 | E5: =YEAR(C5) -> 2023 | F5: =_xlfn.DAYS(D5,C5) -> 5
A6: 5 | B6: David Lee | C6: 45174 | D6: 45179 | E6: =YEAR(C6) -> 2023 | F6: =_xlfn.DAYS(D6,C6) -> 5
A7: 6 | B7: Emily Wang | C7: 45242 | D7: 45245 | E7: =YEAR(C7) -> 2023 | F7: =_xlfn.DAYS(D7,C7) -> 3
A8: 7 | B8: Chris Chen | C8: 45299 | D8: 45303 | E8: =YEAR(C8) -> 2024 | F8: =_xlfn.DAYS(D8,C8) -> 4
A11: How Many Bookings were made in 2023? | B11: =COUNTIFS(C2:C8,">=01/01/2023",C2:C8,"<=31/12/2023") -> 5
A12: What is the average length of stay (in days) for these bookings | B12: =AVERAGE(F2:F8) -> 4.2857143

Sheet Extracting Last Digits of VRN
A1: Vehicle Registeration Number | B1: Vehicle Type | C1: Manufacturing Year | D1: Registeration State | E1: Last Digits of Registeration
A2: DL3CA1234 | B2: Hatchback | C2: 2018 | D2: Delhi | E2: =RIGHT(A2,4) -> 1234
A3: MH12AB5678 | B3: Sedan | C3: 2019 | D3: Maharashtra | E3: =RIGHT(A3,4) -> 5678
A4: KA01CD9876 | B4: SUV | C4: 2020 | D4: Karnataka | E4: =RIGHT(A4,4) -> 9876
A5: GJ05EF2345 | B5: Hatchback | C5: 2017 | D5: Gujarat | E5: =RIGHT(A5,4) -> 2345
A6: TN07GH8765 | B6: Sedan | C6: 2016 | D6: Tamil Nadu | E6: =RIGHT(A6,4) -> 8765
A7: HR02IJ3456 | B7: SUV | C7: 2021 | D7: Haryana | E7: =RIGHT(A7,4) -> 3456
A8: RJ03KL6789 | B8: Hatchback | C8: 2015 | D8: Rajasthan | E8: =RIGHT(A8,4) -> 6789
A9: UP04MN4321 | B9: Sedan | C9: 2014 | D9: Uttar Pradesh | E9: =RIGHT(A9,4) -> 4321
A10: PB05OP1234 | B10: SUV | C10: 2013 | D10: Punjab | E10: =RIGHT(A10,4) -> 1234
A11: MP06QR7890 | B11: Hatchback | C11: 2012 | D11: Madhya Pradesh | E11: =RIGHT(A11,4) -> 7890

Sheet Managing API Deployment
A1: Project ID | B1: Start Date | C1: Estimated Completion (days) | D1: Planned Deployment Dates | E1: Current Progress
A2: P001 | B2: 46039 | C2: 30 | D2: =B2+C2 -> 46069 | E2: =IF(TODAY()>D2,"Deployed","In Progress") -> Deployed
A3: P002 | B3: 46034 | C3: 45 | D3: =B3+C3 -> 46079 | E3: =IF(TODAY()>D3,"Deployed","In Progress") -> Deployed
A4: P003 | B4: 46024 | C4: 60 | D4: =B4+C4 -> 46084 | E4: =IF(TODAY()>D4,"Deployed","In Progress") -> Deployed
A5: P004 | B5: 46054 | C5: 90 | D5: =B5+C5 -> 46144 | E5: =IF(TODAY()>D5,"Deployed","In Progress") -> In Progress
A6: P005 | B6: 45884 | C6: 120 | D6: =B6+C6 -> 46004 | E6: =IF(TODAY()>D6,"Deployed","In Progress") -> Deployed

Sheet Managing Loan Repayment Dates
A1: Loan Id | B1: Loan Issue Date | C1: Repayment Term (Months) | D1: Loan Due Dates | E1: Overdue Status
A2: 1 | B2: 45724 | C2: 3 | D2: =B2+DATE(,C2,) -> 45784 | E2: =IF(D2<TODAY(),"Overdue","On time") -> Overdue
A3: 2 | B3: 46083 | C3: 2 | D3: =B3+DATE(,C3,) -> 46114 | E3: =IF(D3<TODAY(),"Overdue","On time") -> On time
A4: 3 | B4: 46082 | C4: 4 | D4: =B4+DATE(,C4,) -> 46173 | E4: =IF(D4<TODAY(),"Overdue","On time") -> On time
A5: 4 | B5: 45728 | C5: 1 | D5: =B5+DATE(,C5,) -> 45728 | E5: =IF(D5<TODAY(),"Overdue","On time") -> Overdue
A6: 5 | B6: 45725 | C6: 3 | D6: =B6+DATE(,C6,) -> 45785 | E6: =IF(D6<TODAY(),"Overdue","On time") -> Overdue

Sheet Formatting Customer Names 
A1: Customer Id | B1: Customer Name | C1: Proper Case Name
A2: 101 | B2: john doe | C2: =PROPER(B2) -> John Doe
A3: 102 | B3: JANE SMITH | C3: =PROPER(B3) -> Jane Smith
A4: 103 | B4: rahul kumar | C4: =PROPER(B4) -> Rahul Kumar
A5: 104 | B5: SONALI ROY | C5: =PROPER(B5) -> Sonali Roy
A6: 105 | B6: kapil dev | C6: =PROPER(B6) -> Kapil Dev

Sheet Analyzing Property Listing Ages
A1: Property Id | B1: City | C1: Property Type | D1: Listing Date | E1: Age of Property Listings (In Days)
A2: P001 | B2: Bangalore | C2: Apartment | D2: 45092 | E2: =_xlfn.DAYS(TODAY(),D2) -> 1017
A3: P002 | B3: Mumbai | C3: Villa | D3: 45108 | E3: =_xlfn.DAYS(TODAY(),D3) -> 1001
A4: P003 | B4: Delhi | C4: House | D4: 45117 | E4: =_xlfn.DAYS(TODAY(),D4) -> 992
A5: P004 | B5: Hyderabad | C5: Apartment | D5: 45127 | E5: =_xlfn.DAYS(TODAY(),D5) -> 982
A6: P005 | B6: Pune | C6: Apartment | D6: 45143 | E6: =_xlfn.DAYS(TODAY(),D6) -> 966
A7: P006 | B7: Chennai | C7: Villa | D7: 45153 | E7: =_xlfn.DAYS(TODAY(),D7) -> 956
A8: P007 | B8: Kolkata | C8: House | D8: 45170 | E8: =_xlfn.DAYS(TODAY(),D8) -> 939
A9: P008 | B9: Ahmedabad | C9: Apartment | D9: 45719 | E9: =_xlfn.DAYS(TODAY(),D9) -> 390
A10: P009 | B10: Gurugram | C10: Apartment | D10: 46054 | E10: =_xlfn.DAYS(TODAY(),D10) -> 55
A11: P010 | B11: Jaipur | C11: House | D11: 46084 | E11: =_xlfn.DAYS(TODAY(),D11) -> 25
B15: Average Age of Properties by City | E15: Bangalore | F15: =AVERAGEIF(B2:B11,"Bangalore",E2:E11) -> 1017

Sheet Advanced Portfolio Analysis
A1: Client Id | B1: Client Name | C1: Stock Symbol | D1: Quantity | E1: Purchase Price | F1: Current Price | G1: Portfolio Value
A2: 1 | B2: Rajesh Kumar | C2: TCS | D2: 50 | E2: 3000 | F2: 3200 | G2: 160000
A3: 2 | B3: Anjali Sharma | C3: INFY | D3: 100 | E3: 1500 | F3: 1400 | G3: 140000
A4: 3 | B4: Vivek Gupta | C4: RELIANCE | D4: 200 | E4: 2000 | F4: 2100 | G4: 420000
A5: 4 | B5: Sneha Patel | C5: HDFC | D5: 150 | E5: 1800 | F5: 1900 | G5: 285000
A6: 5 | B6: Amit Rao | C6: ICICIBANK | D6: 80 | E6: 400 | F6: 420 | G6: 33600
A7: 6 | B7: Priya Mehta | C7: WIPRO | D7: 120 | E7: 500 | F7: 490 | G7: 58800
A8: 7 | B8: Manish Agarwal | C8: SBI | D8: 250 | E8: 350 | F8: 360 | G8: 90000
A9: 8 | B9: Kavita Joshi | C9: HCLTECH | D9: 70 | E9: 900 | F9: 950 | G9: 66500
A10: 9 | B10: Rohan Das | C10: BHARTIAIRTL | D10: 60 | E10: 650 | F10: 700 | G10: 42000
A11: 10 | B11: Neha Verma | C11: AXISBANK | D11: 90 | E11: 700 | F11: 720 | G11: 64800
B13: Row Number of | C13: Vivek Gupta | D13: =MATCH("Vivek Gupta",B2:B11,0) -> 3
B14: Purchase Price of | C14: HDFC | D14: =VLOOKUP(C14,C1:G11,2,FALSE) -> 150
B15: Current Price of | C15: ICICIBANK | D15: =VLOOKUP(C15,C1:G11,4) -> 420

Sheet Calculating Tiered Discounts
A1: Customer Name | B1: Total Purchase Amount | C1: Loyalty Tier | D1: Discount % | E1: Discount Applied | F1: Final Cost
A2: Radha | B2: 8500 | C2: =IF(AND(B2>=10000, B2<20000), "Platinum", IF(AND(B2>=5000, B2<10000), "Gold", IF(AND(B2>=2000, B2<5000), "Silver", IF(B2<2000, "Regular", "Not Suitable")))) -> Gold | D2: =IF(C2="Platinum","15%", IF(C2="Gold","10%", IF(C2="Silver","5%", IF(C2="Regular","No Discount","")))) -> 10% | E2: =D2*B2 -> 850 | F2: =B2-E2 -> 7650
A3: Suresh | B3: 3000 | C3: =IF(AND(B3>=10000, B3<20000), "Platinum", IF(AND(B3>=5000, B3<10000), "Gold", IF(AND(B3>=2000, B3<5000), "Silver", IF(B3<2000, "Regular", "Not Suitable")))) -> Silver | D3: =IF(C3="Platinum","15%", IF(C3="Gold","10%", IF(C3="Silver","5%", IF(C3="Regular","No Discount","")))) -> 5% | E3: =D3*B3 -> 150 | F3: =B3-E3 -> 2850
A4: Priya | B4: 12000 | C4: =IF(AND(B4>=10000, B4<20000), "Platinum", IF(AND(B4>=5000, B4<10000), "Gold", IF(AND(B4>=2000, B4<5000), "Silver", IF(B4<2000, "Regular", "Not Suitable")))) -> Platinum | D4: =IF(C4="Platinum","15%", IF(C4="Gold","10%", IF(C4="Silver","5%", IF(C4="Regular","No Discount","")))) -> 15% | E4: =D4*B4 -> 1800 | F4: =B4-E4 -> 10200

Sheet Analyzing the Relationship
A1: Month | B1: Deliveries | C1: Customer Satisfaction
A2: January | B2: 15000 | C2: 8.2
A3: February | B3: 16000 | C3: 8
A4: March | B4: 17000 | C4: 7.8
A5: April | B5: 18000 | C5: 7.5
A6: May | B6: 19000 | C6: 7.2
A7: June | B7: 20000 | C7: 7
A8: July | B8: 21000 | C8: 6.8
A9: August | B9: 22000 | C9: 6.5
A10: September | B10: 23000 | C10: 6.3
A11: October | B11: 24000 | C11: 6
A12: November | B12: 25000 | C12: 5.8
A13: December | B13: 26000 | C13: 5.5
A15: Correlation Coefficient | B15: =CORREL(B2:B13,C2:C13) -> -0.99930529

Sheet Analyzing Customer Satisfaction
A1: Transaction ID | B1: Customer ranking | C1: Percentile Rank
A2: T001 | B2: 4 | C2: =_xlfn.PERCENTRANK.INC($B$2:$B$11, B2) -> 0.555
A3: T002 | B3: 2 | C3: =_xlfn.PERCENTRANK.INC($B$2:$B$11, B3) -> 0.111
A4: T003 | B4: 5 | C4: =_xlfn.PERCENTRANK.INC($B$2:$B$11, B4) -> 0.888
A5: T004 | B5: 3 | C5: =_xlfn.PERCENTRANK.INC($B$2:$B$11, B5) -> 0.333
A6: T005 | B6: 4 | C6: =_xlfn.PERCENTRANK.INC($B$2:$B$11, B6) -> 0.555
A7: T006 | B7: 1 | C7: =_xlfn.PERCENTRANK.INC($B$2:$B$11, B7) -> 0
A8: T007 | B8: 3 | C8: =_xlfn.PERCENTRANK.INC($B$2:$B$11, B8) -> 0.333
A9: T008 | B9: 2 | C9: =_xlfn.PERCENTRANK.INC($B$2:$B$11, B9) -> 0.111
A10: T009 | B10: 5 | C10: =_xlfn.PERCENTRANK.INC($B$2:$B$11, B10) -> 0.888
A11: T010 | B11: 4 | C11: =_xlfn.PERCENTRANK.INC($B$2:$B$11, B11) -> 0.555

Sheet Analyzing Daily Transaction
A1: Date | B1: Transaction Count | C1: Truncated Amount
A2: 45474 | B2: 12345.67 | C2: =TRUNC(B2) -> 12345
A3: 45475 | B3: 9876.54 | C3: =TRUNC(B3) -> 9876
A4: 45476 | B4: 4567.89 | C4: =TRUNC(B4) -> 4567
A5: 45477 | B5: 11234.56 | C5: =TRUNC(B5) -> 11234
A6: 45478 | B6: 7890.12 | C6: =TRUNC(B6) -> 7890
A7: 45479 | B7: 5432.1 | C7: =TRUNC(B7) -> 5432
A8: 45480 | B8: 6789.34 | C8: =TRUNC(B8) -> 6789

Sheet Retrieving Product Information
A1: Product ID | B1: Product Name | C1: Category | D1: Price
A2: A001 | B2: AI Chatbot | C2: Software | D2: 15000
A3: A002 | B3: AI Analytics | C3: Software | D3: 25000
A4: A003 | B4: Machine Learning | C4: Training | D4: 20000
A5: A004 | B5: Data Processing | C5: Service | D5: 30000
A6: A005 | B6: Image Recognition | C6: Software | D6: 35000
A8: Product ID | B8: Product Name | C8: Category | D8: Price (INR)
A9: A002 | B9: =VLOOKUP(A9,A1:D6,2,FALSE) -> AI Analytics | C9: =VLOOKUP(B9,B1:D6,2,FALSE) -> Software | D9: =VLOOKUP(B9,B1:D6,3,FALSE) -> 25000
A10: A005 | B10: =VLOOKUP(A10,A1:D6,2,FALSE) -> Image Recognition | C10: =VLOOKUP(B10,B1:D6,2,FALSE) -> Software | D10: =VLOOKUP(B10,B1:D6,3,FALSE) -> 35000
A11: A001 | B11: =VLOOKUP(A11,A1:D6,2,FALSE) -> AI Chatbot | C11: =VLOOKUP(B11,B1:D6,2,FALSE) -> Software | D11: =VLOOKUP(B11,B1:D6,3,FALSE) -> 15000

Sheet Extracting Movie Genres
A1: Movie Title | B1: Movie Genre
A2: Avtar-Action | B2: =TRIM(RIGHT(A2,LEN(A2)-FIND("-",A2))) -> Action
A3: Inception-Sci-Fi | B3: =TRIM(RIGHT(A3,LEN(A3)-FIND("-",A3))) -> Sci-Fi
A4: The Dark Knight-Action | B4: =TRIM(RIGHT(A4,LEN(A4)-FIND("-",A4))) -> Action
A5: Titanic-Romance | B5: =TRIM(RIGHT(A5,LEN(A5)-FIND("-",A5))) -> Romance
A6: Interstellar-Sci-Fi | B6: =TRIM(RIGHT(A6,LEN(A6)-FIND("-",A6))) -> Sci-Fi
A7: Joker-Drama | B7: =TRIM(RIGHT(A7,LEN(A7)-FIND("-",A7))) -> Drama
A8: Avengers:Endgame-Action | B8: =TRIM(RIGHT(A8,LEN(A8)-FIND("-",A8))) -> Action
A9: The Lion King-Animation | B9: =TRIM(RIGHT(A9,LEN(A9)-FIND("-",A9))) -> Animation
A10: Bahubali: The Beginning - Action | B10: =TRIM(RIGHT(A10,LEN(A10)-FIND("-",A10))) -> Action
A11: Dangal-Drama | B11: =TRIM(RIGHT(A11,LEN(A11)-FIND("-",A11))) -> Drama

Sheet Server Performance Variance 
A1: Server ID | B1: Day 1 | C1: Day 2 | D1: Day 3 | E1: Day 4 | F1: Day 5 | G1: Day 6 | H1: Day 7 | I1: Response Variance Time
A2: S001 | B2: 120 | C2: 150 | D2: 130 | E2: 140 | F2: 125 | G2: 135 | H2: 145 | I2: =ROUND(_xlfn.VAR.S(B2:H2),2) -> 116.67
A3: S002 | B3: 200 | C3: 210 | D3: 205 | E3: 220 | F3: 215 | G3: 225 | H3: 230 | I3: =ROUND(_xlfn.VAR.S(B3:H3),2) -> 116.67
A4: S003 | B4: 90 | C4: 85 | D4: 95 | E4: 100 | F4: 110 | G4: 105 | H4: 115 | I4: =ROUND(_xlfn.VAR.S(B4:H4),2) -> 116.67
A5: S004 | B5: 180 | C5: 190 | D5: 185 | E5: 195 | F5: 200 | G5: 195 | H5: 205 | I5: =ROUND(_xlfn.VAR.S(B5:H5),2) -> 73.81
A6: S005 | B6: 160 | C6: 170 | D6: 165 | E6: 175 | F6: 180 | G6: 175 | H6: 185 | I6: =ROUND(_xlfn.VAR.S(B6:H6),2) -> 73.81

Sheet Average Transaction Value
A1: Transaction Id | B1: Recharge Amount
A2: T1234 | B2: 150
A3: T5678 | B3: 220
A4: T8901 | B4: 100
A5: T8902 | B5: 110
A6: T9876 | B6: 120
A7: T9843 | B7: 130
A8: T7262 | B8: 145
A9: T7312 | B9: 110
A10: T8112 | B10: 90
A11: T9912 | B11: 76
A12: T0928 | B12: 110
A13: T1233 | B13: 131
A14: T8764 | B14: 100
A16: Answer | B16: =AVERAGE(B2:B14) -> 122.46154

Sheet Discount Offer Management
A1: Product Id | B1: Product Name | C1: Original Price | D1: Discount % | E1: Discounted Price
A2: AJPR001 | B2: Blue Denim Jeans | C2: 1299 | D2: =VLOOKUP(A2,A11:D16,2,FALSE) -> 17 | E2: =C2-D2/100*C2 -> 1078.17
A3: AJPR002 | B3: Floral Printed Dress | C3: 1850 | D3: =VLOOKUP(A3,A12:D17,2,FALSE) -> 18 | E3: =C3-D3/100*C3 -> 1517
A4: AJPR003 | B4: Black Leather Jacket | C4: 3499 | D4: =VLOOKUP(A4,A13:D18,2,FALSE) -> 20 | E4: =C4-D4/100*C4 -> 2799.2
A5: AJPR004 | B5: White Sneakers | C5: 899 | D5: =VLOOKUP(A5,A14:D19,2,FALSE) -> 15 | E5: =C5-D5/100*C5 -> 764.15
A6: AJPR005 | B6: Sports T-Shirt | C6: 549 | D6: =VLOOKUP(A6,A15:D20,2,FALSE) -> 20 | E6: =C6-D6/100*C6 -> 439.2
A11: Product Id | B11: Discount % | C11: Valid From | D11: Valid To
A12: AJPR001 | B12: 17 | C12: 45419 | D12: 45572
A13: AJPR002 | B13: 18 | C13: 45419 | D13: 45572
A14: AJPR003 | B14: 20 | C14: 45419 | D14: 45572
A15: AJPR004 | B15: 15 | C15: 45480 | D15: 45633
A16: AJPR005 | B16: 20 | C16: 45480 | D16: 45633

Sheet Hourly Flight Booking Analysis
A1: Customer Name | B1: Booking Time | C1: Booking Hour
A2: Reliance | B2: 0.4375 | C2: =HOUR(B2) -> 10
A3: TCS | B3: 0.53125 | C3: =HOUR(B3) -> 12
A4: Infosys | B4: 0.59375 | C4: =HOUR(B4) -> 14
A5: HDFC Bank | B5: 0.66666667 | C5: =HOUR(B5) -> 16
A6: ICICI Bank | B6: 0.77083333 | C6: =HOUR(B6) -> 18

Sheet Identifying Invalid Transaction
A1: Transaction ID | B1: Investor Name | C1: Transaction Amount | D1: Valid Transaction?
A2: T001 | B2: Anil Kumar | C2: 5000 | D2: =IF(AND(B2<>0,C2<>0),TRUE,FALSE) -> TRUE
B3: Sneha Sharma | C3: 15000 | D3: =IF(AND(B3<>0,C3<>0),TRUE,FALSE) -> TRUE
A4: T003 | B4: Ajay Singh | D4: =IF(AND(B4<>0,C4<>0),TRUE,FALSE) -> FALSE
A5: T004 | B5: Priya Verma | C5: 12000 | D5: =IF(AND(B5<>0,C5<>0),TRUE,FALSE) -> TRUE
A6: T005 | B6: Rahul Mehta | C6: 3000 | D6: =IF(AND(B6<>0,C6<>0),TRUE,FALSE) -> TRUE
A7: T006 | B7: Anjali Patel | C7: 20000 | D7: =IF(AND(B7<>0,C7<>0),TRUE,FALSE) -> TRUE
A8: T007 | B8: Vivek Anand | C8: 10000 | D8: =IF(AND(B8<>0,C8<>0),TRUE,FALSE) -> TRUE
A9: T008 | B9: Kavita Rao | D9: =IF(AND(B9<>0,C9<>0),TRUE,FALSE) -> FALSE
B10: Manish Tiwari | C10: 2500 | D10: =IF(AND(B10<>0,C10<>0),TRUE,FALSE) -> TRUE
A11: T010 | B11: Pooja Joshi | C11: 18000 | D11: =IF(AND(B11<>0,C11<>0),TRUE,FALSE) -> TRUE

Sheet Identifying the Minimum Order V
A1: Order id | B1: Prooduct Category | C1: Order Value
A2: O001 | B2: Clothing | C2: 1500
A3: O002 | B3: Electronics | C3: 2500
A4: O003 | B4: Home Décor | C4: 1800
A5: O004 | B5: Clothing | C5: 1200
A6: O005 | B6: Electronics | C6: 3000
A7: O006 | B7: Home Décor | C7: 1000
A8: O007 | B8: Clothing | C8: 2000
A9: O008 | B9: Electronics | C9: 1500
A10: O009 | B10: Home Décor | C10: 2000
A11: O010 | B11: Clothing | C11: 1800
A13: Product Category | B13: Minimum Order Value
A14: Clothing | B14: {=MIN(IF($B$2:$B$11="Clothing", $C$2:$C$11))} -> 1200
A15: Electronics | B15: {=MIN(IF($B$2:$B$11="Electronics", $C$2:$C$11))} -> 1500
A16: Home Décor | B16: {=MIN(IF($B$2:$B$11="Home Décor", $C$2:$C$11))} -> 1000

Sheet Updating Travel Package Codes
A1: Package Id | B1: Package Code | C1: Updated Package Code
A2: 1 | B2: IN-OLD-DELHI-2023 | C2: =SUBSTITUTE(B2,"OLD","NEW") -> IN-NEW-DELHI-2023
A3: 2 | B3: IN-OLD-GOA-2023 | C3: =SUBSTITUTE(B3,"OLD","NEW") -> IN-NEW-GOA-2023
A4: 3 | B4: IN-OLD-MUMBAI-2023 | C4: =SUBSTITUTE(B4,"OLD","NEW") -> IN-NEW-MUMBAI-2023
A5: 4 | B5: IN-OLD-KERALA-2023 | C5: =SUBSTITUTE(B5,"OLD","NEW") -> IN-NEW-KERALA-2023
A6: 5 | B6: IN-OLD-AGRA-2023 | C6: =SUBSTITUTE(B6,"OLD","NEW") -> IN-NEW-AGRA-2023

Sheet Analyzing Customer Eligibility 
A1: Customer Id | B1: Customer Name | C1: Number of Rides | D1: Total Spend Last 6 Months | E1: Qualifies for Ola Premium
A2: C001 | B2: Anil Kumar | C2: 45 | D2: 8500 | E2: =IF(AND(C2>=50,D2>=10000),"Yes","No") -> No
A3: C002 | B3: Priya Sharma | C3: 55 | D3: 11200 | E3: =IF(AND(C3>=50,D3>=10000),"Yes","No") -> Yes
A4: C003 | B4: Rohit Verma | C4: 30 | D4: 6000 | E4: =IF(AND(C4>=50,D4>=10000),"Yes","No") -> No
A5: C004 | B5: Sunil Rao | C5: 60 | D5: 12500 | E5: =IF(AND(C5>=50,D5>=10000),"Yes","No") -> Yes
A6: C005 | B6: Rajesh Singh | C6: 25 | D6: 9800 | E6: =IF(AND(C6>=50,D6>=10000),"Yes","No") -> No
A7: C006 | B7: Neha Gupta | C7: 70 | D7: 15000 | E7: =IF(AND(C7>=50,D7>=10000),"Yes","No") -> Yes
A8: C007 | B8: Manish Tiwari | C8: 40 | D8: 7500 | E8: =IF(AND(C8>=50,D8>=10000),"Yes","No") -> No
A9: C008 | B9: Kavita Patel | C9: 20 | D9: 4500 | E9: =IF(AND(C9>=50,D9>=10000),"Yes","No") -> No
A10: C009 | B10: Rakesh Mehra | C10: 65 | D10: 13000 | E10: =IF(AND(C10>=50,D10>=10000),"Yes","No") -> Yes
A11: C010 | B11: Pooja Joshi | C11: 55 | D11: 10500 | E11: =IF(AND(C11>=50,D11>=10000),"Yes","No") -> Yes

Sheet Extract Code and Description
A1: Product Identifier | B1: Product Code | C1: Product Description
A2: 12345-Milk | B2: =TRIM(LEFT(A2,LEN(A2)-FIND("-",A2))) -> 1234 | C2: =TRIM(RIGHT(A2,LEN(A2)-FIND("-",A2))) -> Milk
A3: 67890-Bread | B3: =TRIM(LEFT(A3,LEN(A3)-FIND("-",A3))) -> 67890 | C3: =TRIM(RIGHT(A3,LEN(A3)-FIND("-",A3))) -> Bread
A4: 11223-Eggs | B4: =TRIM(LEFT(A4,LEN(A4)-FIND("-",A4))) -> 1122 | C4: =TRIM(RIGHT(A4,LEN(A4)-FIND("-",A4))) -> Eggs
A5: 33445-Cheese | B5: =TRIM(LEFT(A5,LEN(A5)-FIND("-",A5))) -> 33445- | C5: =TRIM(RIGHT(A5,LEN(A5)-FIND("-",A5))) -> Cheese
A6: 55667-Vegetables | B6: =TRIM(LEFT(A6,LEN(A6)-FIND("-",A6))) -> 55667-Vege | C6: =TRIM(RIGHT(A6,LEN(A6)-FIND("-",A6))) -> Vegetables
A7: 77889-Fruits | B7: =TRIM(LEFT(A7,LEN(A7)-FIND("-",A7))) -> 77889- | C7: =TRIM(RIGHT(A7,LEN(A7)-FIND("-",A7))) -> Fruits
A8: 99000-Meat | B8: =TRIM(LEFT(A8,LEN(A8)-FIND("-",A8))) -> 9900 | C8: =TRIM(RIGHT(A8,LEN(A8)-FIND("-",A8))) -> Meat
A9: 22334-Fish | B9: =TRIM(LEFT(A9,LEN(A9)-FIND("-",A9))) -> 2233 | C9: =TRIM(RIGHT(A9,LEN(A9)-FIND("-",A9))) -> Fish

Sheet Analyzing Product Sales and Inv
A1: Product Id | B1: Product Name | C1: Price | F1: Product Id | G1: Product Name | H1: Inventory
A2: P001 | B2: Aviator | C2: 2000 | F2: P001 | G2: Aviator | H2: 500
A3: P002 | B3: Wayfarer | C3: 1500 | F3: P002 | G3: Wayfarer | H3: 400
A4: P003 | B4: Cat Eye | C4: 1800 | F4: P003 | G4: Cat Eye | H4: 300
A5: P004 | B5: Round | C5: 2200 | F5: P004 | G5: Round | H5: 450
A6: P005 | B6: Rectangle | C6: 1700 | F6: P005 | G6: Rectangle | H6: 350
A8: Month | B8: P001 | C8: P002 | D8: P003 | E8: P004 | F8: P005 | K8: 150
A9: Jan | B9: 150 | C9: 120 | D9: 90 | E9: 110 | F9: 100 | K9: 130
A10: Feb | B10: 130 | C10: 100 | D10: 85 | E10: 105 | F10: 95 | K10: 140
A11: Mar | B11: 140 | C11: 110 | D11: 100 | E11: 120 | F11: 105 | K11: 145
A12: Apr | B12: 145 | C12: 105 | D12: 95 | E12: 115 | F12: 90 | K12: 150
A13: May | B13: 150 | C13: 115 | D13: 110 | E13: 130 | F13: 110 | K13: =SUM(K8:K12) -> 715
A16: Product ID | B16: Price | C16: Total Sales | D16: Inventory | E16: Sales Revenue
A17: P001 | B17: =VLOOKUP(A17,A1:C6,3,FALSE) -> 2000 | C17: =SUM(INDEX(A9:F13, MATCH(A17, A8:F8, 0), 0)) -> 515 | D17: =VLOOKUP(A17,F1:H6,3,FALSE) -> 500 | E17: =C17*D17 -> 257500
A18: P002 | B18: =VLOOKUP(A18,A2:C7,3,FALSE) -> 1500 | C18: =SUM(INDEX(A9:F13, MATCH(A18, A8:F8, 0), 0)) -> 575 | D18: =VLOOKUP(A18,F2:H7,3,FALSE) -> 400 | E18: =C18*D18 -> 230000
A19: P003 | B19: =VLOOKUP(A19,A3:C8,3,FALSE) -> 1800 | C19: =SUM(INDEX(A9:F13, MATCH(A19, A8:F8, 0), 0)) -> 550 | D19: =VLOOKUP(A19,F3:H8,3,FALSE) -> 300 | E19: =C19*D19 -> 165000
A20: P004 | B20: =VLOOKUP(A20,A4:C9,3,FALSE) -> 2200 | C20: =SUM(INDEX(A9:F13,MATCH(A20,A8:F8,0),0)) -> 615 | D20: =VLOOKUP(A20,F4:H9,3,FALSE) -> 450 | E20: =C20*D20 -> 276750
A21: P005 | B21: =VLOOKUP(A21,A5:C10,3,FALSE) -> 1700 | C21: =SUM(INDEX(A8:F13, MATCH(A21, A8:F8, 0), 0)) -> 615 | D21: =VLOOKUP(A21,F5:H10,3,FALSE) -> 350 | E21: =C21*D21 -> 215250

Sheet Inventory and Sales Analysis
A1: Table 1:Inventory Data
A3: Product ID | B3: Product Name | C3: Category | D3: Stock Level | E3: Purchase Price
A4: 101 | B4: Blue Light Glasses | C4: Eyewear | D4: 120 | E4: 1500
A5: 102 | B5: Contact Lenses | C5: Eyewear | D5: 300 | E5: 200
A6: 103 | B6: Sunglasses | C6: Eyewear | D6: 150 | E6: 2500
A7: 104 | B7: Anti-Glare Glasses | C7: Eyewear | D7: 200 | E7: 1800
A8: 105 | B8: Reading Glasses | C8: Eyewear | D8: 100 | E8: 1200
A10: Table 2:Sales Data
A12: Product ID | B12: January | C12: February | D12: March | E12: April | F12: May | G12: June
A13: 101 | B13: 50 | C13: 60 | D13: 55 | E13: 70 | F13: 65 | G13: 80
A14: 102 | B14: 100 | C14: 120 | D14: 110 | E14: 130 | F14: 125 | G14: 140
A15: 103 | B15: 80 | C15: 90 | D15: 85 | E15: 95 | F15: 100 | G15: 110
A16: 104 | B16: 70 | C16: 80 | D16: 75 | E16: 85 | F16: 90 | G16: 95
A17: 105 | B17: 40 | C17: 50 | D17: 45 | E17: 60 | F17: 55 | G17: 65
A19: Purchase Price of | D19: Sunglasses | F19: =VLOOKUP(D19,B3:E8,4,FALSE) -> 2500
A20: Sales of Product in Month | C20: April | D20: Contact Lenses | F20: =VLOOKUP(102,A12:G17,5,FALSE) -> 130 | G20: =VLOOKUP(102,A12:G17,5,FALSE) -> 130
A21: Total Sales Over 6 Months | D21: Anti-Glare Glasses | F21: =SUM(VLOOKUP(104,A16:G16,2,FALSE),VLOOKUP(104,A16:G16,3,FALSE),VLOOKUP(104,A16:G16,4,FALSE),VLOOKUP(104,A16:G16,5,FALSE),VLOOKUP(104,A16:G16,6,FALSE),VLOOKUP(104,A16:G16,7,FALSE)) -> 495

Sheet Analyzing Most Common Product
A1: Date | B1: ProductId | C1: Product Name | D1: Category | E1: Units Sold | F1: Category Number
A2: 45297 | B2: P001 | C2: Aloe Vera Gel | D2: Skincare | E2: 150 | F2: 1
A3: 45297 | B3: P002 | C3: Neem Face Wash | D3: Skincare | E3: 200 | F3: 1
A4: 45328 | B4: P003 | C4: Onion Hair Oil | D4: Haircare | E4: 180 | F4: 2 | H4: Skincare | I4: =COUNTIF(D2:D11,H4) -> 6
A5: 45357 | B5: P004 | C5: Vitamin C Serum | D5: Skincare | E5: 220 | F5: 1 | H5: Haircare | I5: =COUNTIF(D3:D12,H5) -> 4
A6: 45357 | B6: P005 | C6: Anti-Pollution Crean | D6: Skincare | E6: 170 | F6: 1
A7: 45388 | B7: P006 | C7: Tea Tree Shampoo | D7: Haircare | E7: 160 | F7: 2
A8: 45418 | B8: P007 | C8: Charcoal Face Mask | D8: Skincare | E8: 190 | F8: 1
A9: 45449 | B9: P008 | C9: Onion Shampoo | D9: Haircare | E9: 200 | F9: 2
A10: 45479 | B10: P009 | C10: Ubtan Face Wash | D10: Skincare | E10: 210 | F10: 1
A11: 45510 | B11: P010 | C11: Argan Hair Mask | D11: Haircare | E11: 140 | F11: 2
A13: Answer | B13: =LARGE(H4:I5,1) -> 6

Sheet Analyzing Sales Data
A1: Month | B1: Western Wear | C1: Ethnic Wear | D1: Accessories | E1: Foot wear | F1: Home Décor
A2: January | B2: 120000 | C2: 150000 | D2: 80000 | E2: 60000 | F2: 70000
A3: February | B3: 130000 | C3: 160000 | D3: 85000 | E3: 65000 | F3: 75000
A4: March | B4: 140000 | C4: 170000 | D4: 90000 | E4: 70000 | F4: 80000
A5: April | B5: 150000 | C5: 180000 | D5: 95000 | E5: 75000 | F5: 85000
A6: May | B6: 160000 | C6: 190000 | D6: 100000 | E6: 80000 | F6: 90000
A7: June | B7: 170000 | C7: 200000 | D7: 105000 | E7: 85000 | F7: 95000
A9: Average Sales of Last 3Months for the Category | B9: Ethnic Wear | C9: =AVERAGE(OFFSET(C5, COUNTA(A5:A7)-3, 0, 3, 1)) -> 190000

Sheet Identifying the Lowest Revenue
A1: Product Id | B1: Product Name | C1: Category | D1: Units Sold | E1: Price per Unit | F1: Total Revenue
A2: P001 | B2: Smartphone A | C2: Electronics | D2: 150 | E2: 10000 | F2: 1500000
A3: P002 | B3: Headphones C | C3: Electronics | D3: 300 | E3: 1500 | F3: 450000
A4: P003 | B4: T-shirt D | C4: Fashion | D4: 500 | E4: 500 | F4: 250000
A5: P004 | B5: Book F | C5: Books | D5: 1000 | E5: 200 | F5: 200000
A6: P005 | B6: Toy H | C6: Toys | D6: 150 | E6: 1000 | F6: 150000
A8: Answer | B8: =MIN(F2:F6) -> 150000

Sheet Analyzing Student Performance
A1: Student Id | B1: Score
A2: S01 | B2: 85
A3: S02 | B3: 78
A4: S03 | B4: 92
A5: S04 | B5: 65
A6: S05 | B6: 88
A7: S06 | B7: 76
A8: S07 | B8: 90
A9: S08 | B9: 70
A10: S09 | B10: 60
A11: S10 | B11: 82
A12: S11 | B12: 75
A13: S12 | B13: 68
... A21: S20 | B21: 80
A23: First Quartile | B23: =QUARTILE(B2:B21,1) -> 72.75
A24: Second Quartile | B24: =QUARTILE(B2:B21,2) -> 79
A25: Third Quartile | B25: =QUARTILE(B2:B21,3) -> 85.75

Sheet Analyzing Customer Reviews
A1: Product Name | B1: Review ID | C1: Review Content | D1: Keyword | E1: Keyword found position
A2: Redmi Note 10 | B2: 1001 | C2: "Great battery life and excellent camera quality" | D2: battery | E2: =FIND(D2,C2,1) -> 8
A3: Mi Smart Band | B3: 1002 | C3: "Affordable and featured-packed fitness tracker" | D3: fitness | E3: =FIND(D3,C3,1) -> 33
A4: Boat Headphones | B4: 1003 | C4: "Superb sound quality but a bit uncomfortable for long use" | D4: sound | E4: =FIND(D4,C4,1) -> 9
A5: HP Laptop | B5: 1004 | C5: "Fast performance with a sleek design, but battery drains quickly" | D5: design | E5: =FIND(D5,C5,1) -> 32
A6: Samsung Galaxy Tab | B6: 1005 | C6: "Excellent display and battery lif, but a bit pricey" | D6: display | E6: =FIND(D6,C6,1) -> 12

Sheet Analyzing Course Performance
A1: Course ID | B1: Course Name | C1: Instructor ID
A2: C101 | B2: Basic Math | C2: I001
A3: C102 | B3: Advanced Physics | C3: I002
A4: C103 | B4: Indian History | C4: I003
A5: C104 | B5: English Literature | C5: I004
A6: C105 | B6: Data Science Essentials | C6: I005
A10: Instructor ID | B10: Name | C10: Avg Rating | D10: Courses Taught
A11: I001 | B11: Dr.Sharma | C11: 4.5 | D11: 3
A12: I002 | B12: Prof.Singh | C12: 4.7 | D12: 2
A13: I003 | B13: Dr.Verma | C13: 4.3 | D13: 5
A14: I004 | B14: Prof.Kapoor | C14: 4.8 | D14: 4
A15: I005 | B15: Dr.Mishra | C15: 4.6 | D15: 3
A19: Course ID | B19: Total Enrollments
A20: C101 | B20: 1200
A21: C102 | B21: 850
A22: C103 | B22: 900
A23: C104 | B23: 750
A24: C105 | B24: 1150
A27: Course Id | B27: Course Name | C27: Instructor Name | D27: Average Rating | E27: Total Enrollments
A28: C101 | B28: =VLOOKUP(A28,A1:C6,2,FALSE) -> Basic Math | C28: =VLOOKUP(C2,$A$10:$D$15,2,FALSE) -> Dr.Sharma | D28: =VLOOKUP(C28,$B$10:$D$15,2,FALSE) -> 4.5 | E28: =VLOOKUP(A28,$A$19:$B$24,2,FALSE) -> 1200
A29: C102 | B29: =VLOOKUP(A29,$A$1:$C$6,2,FALSE) -> Advanced Physics | C29: =VLOOKUP(C3,$A$10:$D$15,2,FALSE) -> Prof.Singh | D29: =VLOOKUP(C29,$B$10:$D$15,2,FALSE) -> 4.7 | E29: =VLOOKUP(A29,$A$19:$B$24,2,FALSE) -> 850
A30: C103 | B30: =VLOOKUP(A30,$A$1:$C$6,2,FALSE) -> Indian History | C30: =VLOOKUP(C4,$A$10:$D$15,2,FALSE) -> Dr.Verma | D30: =VLOOKUP(C30,$B$10:$D$15,2,FALSE) -> 4.3 | E30: =VLOOKUP(A30,$A$19:$B$24,2,FALSE) -> 900
A31: C104 | B31: =VLOOKUP(A31,$A$1:$C$6,2,FALSE) -> English Literature | C31: =VLOOKUP(C5,$A$10:$D$15,2,FALSE) -> Prof.Kapoor | D31: =VLOOKUP(C31,$B$10:$D$15,2,FALSE) -> 4.8 | E31: =VLOOKUP(A31,$A$19:$B$24,2,FALSE) -> 750
A32: C105 | B32: =VLOOKUP(A32,$A$1:$C$6,2,FALSE) -> Data Science Essentials | C32: =VLOOKUP(C6,$A$10:$D$15,2,FALSE) -> Dr.Mishra | D32: =VLOOKUP(C32,$B$10:$D$15,2,FALSE) -> 4.6 | E32: =VLOOKUP(A32,$A$19:$B$24,2,FALSE) -> 1150

Sheet Cleaning Customer Data

Sheet Analyzing Investment Portfolio 
A1: Stock Name | B1: Number of Share | C1: Stock price
A2: HDFC Bank | B2: 250 | C2: 1550
A3: Reliance | B3: 150 | C3: 2485
A4: Infosys | B4: 300 | C4: 1760
A5: TCS | B5: 200 | C5: 3050
A6: HCL Technologies | B6: 180 | C6: 1200
A7: Wipro | B7: 220 | C7: 650
A8: ICICI Bank | B8: 180 | C8: 670
A9: Axis Bank | B9: 150 | C9: 800
A10: SBI | B10: 300 | C10: 450
A11: Tech Mahindra | B11: 200 | C11: 1100
A13: Total Investment Value | B13: =B2*C2+B3*C3+B4*C4+B5*C5+B6*C6+B7*C7+B8*C8+B9*C9+B10*C10+B11*C11 -> 2852850
A14: Average Stock Price | B14: =AVERAGE(C2:C11) -> 1371.5
A15: Number of Stocks in Portfolio | B15: =COUNTA(A2:A11) -> 10

Sheet API Response Time Analysis
A1: API Endpoint | B1: Response Interval 1 (ms) | C1: Response Interval 2 (ms) | D1: Response Interval 3 (ms) | E1: Response Interval 4 (ms) | F1: Response Interval 5 (ms) | G1: Max Response Time | H1: Max Response Cell
A2: /user/login | B2: 120 | C2: 150 | D2: 110 | E2: 170 | F2: 130 | G2: =MATCH(MAX(B2:F2),B2:F2,0) -> 4 | H2: =ADDRESS(ROW(B2),MATCH(MAX(B2:F2),B2:F2,0)+COLUMN(B2)-1) -> $E$2
A3: /user/signup | B3: 100 | C3: 180 | D3: 160 | E3: 140 | F3: 190 | G3: =MATCH(MAX(B3:F3),B3:F3,0) -> 5 | H3: =ADDRESS(ROW(B3),MATCH(MAX(B3:F3),B3:F3,0)+COLUMN(B3)-1) -> $F$3
A4: /data/fetch | B4: 200 | C4: 210 | D4: 190 | E4: 220 | F4: 180 | G4: =MATCH(MAX(B4:F4),B4:F4,0) -> 4 | H4: =ADDRESS(ROW(B4),MATCH(MAX(B4:F4),B4:F4,0)+COLUMN(B4)-1) -> $E$4
A5: /data/update | B5: 140 | C5: 130 | D5: 150 | E5: 160 | F5: 170 | G5: =MATCH(MAX(B5:F5),B5:F5,0) -> 5 | H5: =ADDRESS(ROW(B5),MATCH(MAX(B5:F5),B5:F5,0)+COLUMN(B5)-1) -> $F$5
A6: /data/delete | B6: 180 | C6: 170 | D6: 190 | E6: 200 | F6: 210 | G6: =MATCH(MAX(B6:F6),B6:F6,0) -> 5 | H6: =ADDRESS(ROW(B6),MATCH(MAX(B6:F6),B6:F6,0)+COLUMN(B6)-1) -> $F$6

Sheet Optimizing Electric Vehicle
A1: Vehicle Id | B1: Arrival Time | C1: Battery Level | D1: Charging Station | E1: Charging Duration | F1: Optimal Start Charging Time | G1: Charging Completion Time
A2: V001 | B2: 7/15/2024 10:00 | C2: 60 | D2: A | E2: 120 | F2: =DATE(2024,7,15)+TIME(10,0,0)+TIME(1,0,0) -> 45488.458 | G2: =E2/1440+F2 -> 45488.542
A3: V002 | B3: 7/15/2024 12:30 | C3: 40 | D3: B | E3: 90 | F3: =DATE(2024,7,15)+TIME(12,30,0)+TIME(0,30,0) -> 45488.542 | G3: =E3/1440+F3 -> 45488.604
A4: V003 | B4: 7/15/2024 15:45 | C4: 80 | D4: A | E4: 150 | F4: =DATE(2024,7,15)+TIME(15,45,0)+TIME(1,0,0) -> 45488.698 | G4: =E4/1440+F4 -> 45488.802
A5: V004 | B5: 7/15/2024 18:00 | C5: 30 | D5: C | E5: 60 | F5: =DATE(2024,7,15)+TIME(18,0,0)+TIME(0,30,0) -> 45488.771 | G5: =E5/1440+F5 -> 45488.812
A6: V005 | B6: 7/15/2024 20:30 | C6: 70 | D6: B | E6: 120 | F6: =DATE(2024,7,15)+TIME(20,30,0)+TIME(0,30,0) -> 45488.875 | G6: =E6/1440+F6 -> 45488.958

Sheet Advanced Sales Performance 
A1: Product Name | B1: Units Sold | C1: Unit Price(INR) | D1: Remaining Inventory | E1: Cost per Unit
A2: Boat Earphones | B2: 1500 | C2: 999 | D2: 500 | E2: 400
A3: Boat Headphones | B3: 800 | C3: 1999 | D3: 300 | E3: 800
A4: Boat Speakers | B4: 500 | C4: 2999 | D4: 200 | E4: 1500
A5: Boat Smartwatches | B5: 400 | C5: 4999 | D5: 150 | E5: 2500
A6: Boat Soundbars | B6: 300 | C6: 6999 | D6: 100 | E6: 3500
A7: Boat Chargers | B7: 2000 | C7: 299 | D7: 800 | E7: 100
A8: Boat Powerbarnks | B8: 1200 | C8: 999 | D8: 400 | E8: 500
A9: Boat Cables | B9: 2500 | C9: 199 | D9: 1000 | E9: 50
A10: Boat Wireless Earbuds | B10: 1800 | C10: 2999 | D10: 600 | E10: 1200
A11: Boat Bluetooth Speakers | B11: 700 | C11: 1999 | D11: 300 | E11: 800
A13: Total Sales Revenue | B13: =B2*C2+B3*C3+B4*C4+B5*C5+B6*C6+B7*C7+B8*C8+B9*C9+B10*C10+B11*C11 -> 17788300
A14: Weighted Average Cost per Unit | D14: =B2*E2+B3*E3+B4*E4+B5*E5+B6*E6+B7*E7+B8*E8+B9*E9+B10*E10+B11*E11 -> 7685000 | E14: =B2+B3+B4+B5+B6+B7+B8+B10+B9+B11 -> 11700
A15: Total Profit | B15: =B13-(B2*E2+B3*E3+B4*E4+B5*E5+B6*E6+B7*E7+B8*E8+B9*E9+B10*E10+B11*E11) -> 10103300
A16: Rounded Profit Margin | B16: =B15/B13*100 -> 56.797446

Sheet Methods for Splitting Cell Valu
A1: City,Country | B1: Population
A2: Tokyo,JP | B2: 37339804
A3: Delhi,IN | B3: 31181376
A4: Shanghai,CN | B4: 27795702
A5: Sao Paulo,BR | B5: 22237402
A6: Mexico City,MX | B6: 21918936
A7: Dhaka,BD | B7: 21741090
A8: Cairo,EG | B8: 21322750
A9: Beijing,CN | B9: 20896820
A10: Mumbai,IN | B10: 20667656
A11: Osaka,JP | B11: 19110616
A12: Karachi,PK | B12: 16459472
A13: Chongquiing,CN | B13: 16382376
... A21: Guangzhou,CN | B21: 13635397

Sheet Methods for Splitting Cell (1)
A1: City | B1: Country | C1: Population
A2: Buenos Aires | B2: AR | C2: 15257693
A3: Dhaka | B3: BD | C3: 21741090
A4: Sao Paulo | B4: BR | C4: 22237402
A5: Kinshaha | B5: CD | C5: 14970460
A6: Beijing | B6: CN | C6: 20896820
A7: Chongquiing | B7: CN | C7: 16382376
A8: Guangzhou | B8: CN | C8: 13635397
A9: Shanghai | B9: CN | C9: 27795702
A10: Tianjin | B10: CN | C10: 13794450
A11: Cairo | B11: EG | C11: 21322750
A12: Delhi | B12: IN | C12: 31181376
A13: Kolkata | B13: IN | C13: 14974073
... A21: Istanbul | B21: TR | C21: 15415197

Sheet Using Basic Logical Functions
A1: Employee Name | B1: Department | C1: Tenure (Years) | D1: Vactaion Days (Remaining) | E1: Request Status
A2: Carter Clark | B2: Accounts | C2: 5 | D2: 5 | E2: =IF(OR(C2>=3,D2>5),"Priority"," ") -> Priority
A3: Lisa Loeb | B3: Accounts | C3: 4 | D3: 5 | E3: =IF(OR(C3>=3,D3>5),"Priority"," ") -> Priority
A4: Brandon Butler | B4: Accounts | C4: 2 | D4: 4 | E4: =IF(OR(C4>=3,D4>5),"Priority"," ")
A5: Ingrid Isaacs | B5: Human Resources | C5: 2 | D5: 4 | E5: =IF(OR(C5>=3,D5>5),"Priority"," ")
A6: Kelly Kong | B6: IT | C6: 3 | D6: 6 | E6: =IF(OR(C6>=3,D6>5),"Priority"," ") -> Priority
A7: Jaime Johnson | B7: IT | C7: 1 | D7: 3 | E7: =IF(OR(C7>=3,D7>5),"Priority"," ")
A8: Andrea Atkins | B8: Maintenance | C8: 2 | D8: 10 | E8: =IF(OR(C8>=3,D8>5),"Priority"," ") -> Priority
A9: Dante Dennis | B9: Maintenance | C9: 1 | D9: 0 | E9: =IF(OR(C9>=3,D9>5),"Priority"," ")
A10: Greg Gunther | B10: Sales | C10: 1 | D10: 2 | E10: =IF(OR(C10>=3,D10>5),"Priority"," ")
A11: Harold Hemsworth | B11: Sales | C11: 2 | D11: 8 | E11: =IF(OR(C11>=3,D11>5),"Priority"," ") -> Priority
A12: Farrah Falconi | B12: Sales | C12: 3 | D12: 2 | E12: =IF(OR(C12>=3,D12>5),"Priority"," ") -> Priority
A13: Evadne Erskine | B13: Sales | C13: 2 | D13: 0 | E13: =IF(OR(C13>=3,D13>5),"Priority"," ")
A15: Department | B15: Accounts | C15: IT | D15: Sales | E15: Maintenance | F15: Human Resources
A16: Vacation Days Left | B16: =SUMIF(B1:E13,B15,D2:D13) -> 13 | C16: =SUMIF(B1:E13,C15,D2:D13) -> 13 | D16: =SUMIF(B1:E13,D15,D2:D13) -> 10 | E16: =SUMIF(B1:E13,E15,D2:D13) -> 2 | F16: =SUMIF(B1:E13,E15,D2:D13) -> 2

Sheet  Convert Dates Stored as Text
A1: Name | B1: Type 1 | C1: Speed
A2: Bulbasur | B2: Grass | C2: 45
A3: Ivysaur | B3: Grass | C3: 60
A4: Venusaur | B4: Grass | C4: 80
A5: Charmander | B5: Fire | C5: 65
A6: Charmelon | B6: Fire | C6: 80
A7: Charizard | B7: Fire | C7: 100
A8: Squirtle | B8: Water | C8: 43
A9: Wartotle | B9: Water | C9: 58

Sheet Logical
A1: Name | B1: Type 1 | C1: Speed | D1: Fire Type And more than 70 speed | E1: Water Type or more than 60 defense | F1: Total | G1: Grass Type | H1: More than 500 Total Stats | I1: Speed Category
A2: Bulbasur | B2: Grass | C2: 45 | D2: =AND(B2="Fire",C2>70) -> FALSE | E2: =OR(B2="Water",C2>60) -> FALSE | F2: 318 | G2: =IF(B2="Grass","Yes","No") -> Yes | H2: =IF(F2>500,"Yes","No") -> No | I2: =IF(C2>90,"Fast",IF(C2>50,"Medium",IF(C2<=50,"Slow"))) -> Slow
A3: Ivysaur | B3: Grass | C3: 60 | D3: =AND(B3="Fire",C3>70) -> FALSE | E3: =OR(B3="Water",C3>60) -> FALSE | F3: 405 | G3: =IF(B3="Grass","Yes","No") -> Yes | H3: =IF(F3>500,"Yes","No") -> No | I3: =IF(C3>90,"Fast",IF(C3>50,"Medium",IF(C3<=50,"Slow"))) -> Medium
A4: Venusaur | B4: Grass | C4: 80 | D4: =AND(B4="Fire",C4>70) -> FALSE | E4: =OR(B4="Water",C4>60) -> TRUE | F4: 525 | G4: =IF(B4="Grass","Yes","No") -> Yes | H4: =IF(F4>500,"Yes","No") -> Yes | I4: =IF(C4>90,"Fast",IF(C4>50,"Medium",IF(C4<=50,"Slow"))) -> Medium
A5: Charmander | B5: Fire | C5: 65 | D5: =AND(B5="Fire",C5>70) -> FALSE | E5: =OR(B5="Water",C5>60) -> TRUE | F5: 309 | G5: =IF(B5="Grass","Yes","No") -> No | H5: =IF(F5>500,"Yes","No") -> No | I5: =IF(C5>90,"Fast",IF(C5>50,"Medium",IF(C5<=50,"Slow"))) -> Medium
A6: Charmelon | B6: Fire | C6: 80 | D6: =AND(B6="Fire",C6>70) -> TRUE | E6: =OR(B6="Water",C6>60) -> TRUE | F6: 405 | G6: =IF(B6="Grass","Yes","No") -> No | H6: =IF(F6>500,"Yes","No") -> No | I6: =IF(C6>90,"Fast",IF(C6>50,"Medium",IF(C6<=50,"Slow"))) -> Medium
A7: Charizard | B7: Fire | C7: 100 | D7: =AND(B7="Fire",C7>70) -> TRUE | E7: =OR(B7="Water",C7>60) -> TRUE | F7: 534 | G7: =IF(B7="Grass","Yes","No") -> No | H7: =IF(F7>500,"Yes","No") -> Yes | I7: =IF(C7>90,"Fast",IF(C7>50,"Medium",IF(C7<=50,"Slow"))) -> Fast
A8: Squirtle | B8: Water | C8: 43 | D8: =AND(B8="Fire",C8>70) -> FALSE | E8: =OR(B8="Water",C8>60) -> TRUE | F8: 314 | G8: =IF(B8="Grass","Yes","No") -> No | H8: =IF(F8>500,"Yes","No") -> No | I8: =IF(C8>90,"Fast",IF(C8>50,"Medium",IF(C8<=50,"Slow"))) -> Slow
A9: Wartotle | B9: Water | C9: 58 | D9: =AND(B9="Fire",C9>70) -> FALSE | E9: =OR(B9="Water",C9>60) -> TRUE | F9: 405 | G9: =IF(B9="Grass","Yes","No") -> No | H9: =IF(F9>500,"Yes","No") -> No | I9: =IF(C9>90,"Fast",IF(C9>50,"Medium",IF(C9<=50,"Slow"))) -> Medium
A10: Blastoise | B10: Water | C10: 78 | D10: =AND(B10="Fire",C10>70) -> FALSE | E10: =OR(B10="Water",C10>60) -> TRUE | F10: 530 | G10: =IF(B10="Grass","Yes","No") -> No | H10: =IF(F10>500,"Yes","No") -> Yes | I10: =IF(C10>90,"Fast",IF(C10>50,"Medium",IF(C10<=50,"Slow"))) -> Medium

Sheet NPV
A1: Year | B1: 1 | C1: 2 | D1: 3 | E1: 4 | F1: 5 | G1: 6 | H1: 7 | I1: 8 | J1: 9 | K1: 10
A2: Cash Flow | B2: 10 | C2: 12 | D2: 16 | E2: 20 | F2: 28 | G2: 50 | H2: 80 | I2: 140 | J2: 200 | K2: 250
A5: Discount Rate | B5: 0.1 | D5: NPV | E5: =NPV(B5,A2:K2) -> 377.86809

Sheet Lookup Function
A1: ID# | B1: Name | C1: Type 1 | D1: Type 2 | E1: Total
A2: 1 | B2: Bulbasur | C2: Grass | D2: Poison | E2: 318
A3: 2 | B3: Ivysaur | C3: Grass | D3: Poison | E3: 405 | G3: Search ID# | K3: 4 | L3: 7 | M3: 8 | N3: 13 | O3: 14 | P3: 16 | Q3: 18 | R3: 19 | S3: 12 | T3: 2 | U3: 3 | V3: 4 | W3: 9
A4: 3 | B4: Venusaur | C4: Grass | D4: Poison | E4: 525 | G4: Name | H4: Bulbasur | I4: Squirtle | J4: Rattata | K4: =VLOOKUP(K3,A1:E21,2,TRUE) -> Charmander | L4: =VLOOKUP(L3,A1:E21,2,TRUE) -> Squirtle | M4: =VLOOKUP(M3,A1:E21,2,TRUE) -> Wartotle | N4: =VLOOKUP(N3,A1:E21,2,FALSE) -> Weedle | O4: =VLOOKUP(O3,A1:E21,2,FALSE) -> Kakuna | P4: =VLOOKUP(P3,A1:E21,2,TRUE) -> Pidgey | Q4: =VLOOKUP(Q3,A1:E21,2,TRUE) -> Pidgeot | R4: =VLOOKUP(R3,A1:E21,2,TRUE) -> Rattata | S4: =VLOOKUP(S3,A1:E21,2,FALSE) -> Butterfree | T4: =VLOOKUP(T3,A1:E21,2,TRUE) -> Ivysaur | U4: =VLOOKUP(U3,A1:E21,2,TRUE) -> Venusaur | V4: =VLOOKUP(V3,A1:E21,2,TRUE) -> Charmander | W4: =VLOOKUP(W3,A1:E21,2,TRUE) -> Blastoise
A5: 4 | B5: Charmander | C5: Fire | E5: 309 | G5: Score | H5: =VLOOKUP(H4,B1:E21,4,FALSE) -> 318 | I5: =VLOOKUP(I4,B1:E21,4,FALSE) -> 314 | J5: =VLOOKUP(J4,B1:E21,4,FALSE) -> 253 | K5: =VLOOKUP(K4,B1:E21,4,FALSE) -> 309 | L5: =VLOOKUP(L4,B1:E21,4,FALSE) -> 314 | M5: =VLOOKUP(M4,B1:E21,4,FALSE) -> 405 | N5: =VLOOKUP(N4,B1:E21,4,FALSE) -> 195 | O5: =VLOOKUP(O4,B1:E21,4,FALSE) -> 205 | P5: =VLOOKUP(P4,B1:E21,4,FALSE) -> 251 | Q5: =VLOOKUP(Q4,B1:E21,4,FALSE) -> 479 | R5: =VLOOKUP(R4,B1:E21,4,FALSE) -> 253 | S5: =VLOOKUP(S4,B1:E21,4,FALSE) -> 395 | T5: =VLOOKUP(T4,B1:E21,4,FALSE) -> 405 | U5: =VLOOKUP(U4,B1:E21,4,FALSE) -> 525 | V5: =VLOOKUP(V4,B1:E21,4,FALSE) -> 309 | W5: =VLOOKUP(W4,B1:E21,4,FALSE) -> 530
A6: 5 | B6: Charmelon | C6: Fire | E6: 405 | G6: Type 1 | H6: =VLOOKUP(H4,B1:E21,2,FALSE) -> Grass | I6: =VLOOKUP(I4,B1:E21,2,FALSE) -> Water | J6: =VLOOKUP(J4,B1:E21,2,FALSE) -> Normal | K6: =VLOOKUP(K4,B1:E21,2,FALSE) -> Fire | L6: =VLOOKUP(L4,B1:E21,2,FALSE) -> Water | M6: =VLOOKUP(M4,B1:E21,2,FALSE) -> Water | N6: =VLOOKUP(N4,B1:E21,2,FALSE) -> Bug | O6: =VLOOKUP(O4,B1:E21,2,FALSE) -> Bug | P6: =VLOOKUP(P4,B1:E21,2,FALSE) -> Normal | Q6: =VLOOKUP(Q4,B1:E21,2,FALSE) -> Normal | R6: =VLOOKUP(R4,B1:E21,2,FALSE) -> Normal | S6: =VLOOKUP(S3,A1:E21,3,TRUE) -> Bug | T6: =VLOOKUP(T3,A1:E21,2,TRUE) -> Ivysaur | U6: =VLOOKUP(U3,A1:E21,3,TRUE) -> Grass | V6: =VLOOKUP(V3,A1:E21,3,TRUE) -> Fire | W6: =VLOOKUP(W3,A1:E21,3,TRUE) -> Water
A7: 6 | B7: Charizard | C7: Fire | D7: Flying | E7: 534
A8: 7 | B8: Squirtle | C8: Water | E8: 314
A9: 8 | B9: Wartotle | C9: Water | E9: 405
A10: 9 | B10: Blastoise | C10: Water | E10: 530
A11: 10 | B11: Caterpie | C11: Bug | E11: 195 | J11: STDEV.P | K11: =_xlfn.STDEV.P(E2:E23) -> 108.67284
A12: 11 | B12: Metapod | C12: Bug | E12: 205 | J12: STDEV.S | K12: =_xlfn.STDEV.S(E2:E23) -> 111.23019
A13: 12 | B13: Butterfree | C13: Bug | D13: Flying | E13: 395
A14: 13 | B14: Weedle | C14: Bug | D14: Poison | E14: 195
A15: 14 | B15: Kakuna | C15: Bug | D15: Poison | E15: 205
A16: 15 | B16: Beedrill | C16: Bug | D16: Poison | E16: 395
A17: 16 | B17: Pidgey | C17: Normal | D17: Flying | E17: 251
A18: 17 | B18: Pidgeotto | C18: Normal | D18: Flying | E18: 349
A19: 18 | B19: Pidgeot | C19: Normal | D19: Flying | E19: 479
A20: 19 | B20: Rattata | C20: Normal | E20: 253
A21: 20 | B21: Raticate | C21: Normal | E21: 413
A22: 21 | B22: Spearow | C22: Normal | D22: Flying | E22: 262
A23: 22 | B23: Fearow | C23: Normal | D23: Flying | E23: 442

Sheet XOR
A1: Name | B1: Type 1 | C1: Speed | D1: Either Fire Type or less than 60 hp
A2: Bulbasur | B2: Grass | C2: 45 | D2: =_xlfn.XOR(B2="Fire",C2<60) -> TRUE
A3: Ivysaur | B3: Grass | C3: 60 | D3: =_xlfn.XOR(B3="Fire",C3<60) -> FALSE
A4: Venusaur | B4: Grass | C4: 80 | D4: =_xlfn.XOR(B4="Fire",C4<60) -> FALSE
A5: Charmander | B5: Fire | C5: 65 | D5: =_xlfn.XOR(B5="Fire",C5<60) -> TRUE
A6: Charmelon | B6: Fire | C6: 80 | D6: =_xlfn.XOR(B6="Fire",C6<60) -> TRUE
A7: Charizard | B7: Fire | C7: 100 | D7: =_xlfn.XOR(B7="Fire",C7<60) -> TRUE
A8: Squirtle | B8: Water | C8: 43 | D8: =_xlfn.XOR(B8="Fire",C8<60) -> TRUE
A9: Wartotle | B9: Water | C9: 58 | D9: =_xlfn.XOR(B9="Fire",C9<60) -> TRUE
A10: Blastoise | B10: Water | C10: 78 | D10: =_xlfn.XOR(B10="Fire",C10<60) -> FALSE

Sheet Arithmetic plus Logic
A1: Roll No | B1: Student Name | C1: Hindi | D1: English | E1: Math | F1: Physics | G1: Chemistry | H1: Total | I1: Average | J1: Grade | M1: SRNO | N1: ITEMS | O1: QTY | P1: RATE | Q1: AMOUNT | R1: GRADE
A2: 1 | B2: Ram | C2: 20 | D2: 10 | E2: 14 | F2: 18 | G2: 15 | H2: =SUM(C2:G2) -> 77 | I2: =AVERAGE(C2:G2) -> 15.4 | J2: =IF(I2>15,"A","B") -> A | M2: 1 | N2: AC | O2: 20 | P2: 40000 | Q2: =O2*P2 -> 800000 | R2: =IF(Q2>500000,"Expensive","Lets Buy it") -> Expensive
A3: 2 | B3: Ashok | C3: 21 | D3: 12 | E3: 14 | F3: 12 | G3: 18 | H3: =SUM(C3:G3) -> 77 | I3: =AVERAGE(C3:G3) -> 15.4 | J3: =IF(I3>15,"A","B") -> A | M3: 2 | N3: FRIDGE | O3: 30 | P3: 20000 | Q3: =O3*P3 -> 600000 | R3: =IF(Q3>500000,"Expensive","Lets Buy it") -> Expensive
A4: 3 | B4: Manoj | C4: 33 | D4: 15 | E4: 7 | F4: 14 | G4: 17 | H4: =SUM(C4:G4) -> 86 | I4: =AVERAGE(C4:G4) -> 17.2 | J4: =IF(I4>15,"A","B") -> A | M4: 3 | N4: COOLER | O4: 15 | P4: 10000 | Q4: =O4*P4 -> 150000 | R4: =IF(Q4>500000,"Expensive","Lets Buy it") -> Lets Buy it
A5: 4 | B5: Rajesh | C5: 15 | D5: 14 | E5: 8 | F5: 16 | G5: 20 | H5: =SUM(C5:G5) -> 73 | I5: =AVERAGE(C5:G5) -> 14.6 | J5: =IF(I5>15,"A","B") -> B | M5: 4 | N5: WASHING MACHINE | O5: 14 | P5: 15000 | Q5: =O5*P5 -> 210000 | R5: =IF(Q5>500000,"Expensive","Lets Buy it") -> Lets Buy it
A6: 5 | B6: Ranjana | C6: 14 | D6: 17 | E6: 10 | F6: 13 | G6: 18 | H6: =SUM(C6:G6) -> 72 | I6: =AVERAGE(C6:G6) -> 14.4 | J6: =IF(I6>15,"A","B") -> B | M6: 5 | N6: TV | O6: 18 | P6: 20000 | Q6: =O6*P6 -> 360000 | R6: =IF(Q6>500000,"Expensive","Lets Buy it") -> Lets Buy it
A7: 6 | B7: Pooja | C7: 16 | D7: 8 | E7: 20 | F7: 17 | G7: 15 | H7: =SUM(C7:G7) -> 76 | I7: =AVERAGE(C7:G7) -> 15.2 | J7: =IF(I7>15,"A","B") -> A | M7: 6 | N7: FAN | O7: 17 | P7: 2000 | Q7: =O7*P7 -> 34000 | R7: =IF(Q7>500000,"Expensive","Lets Buy it") -> Lets Buy it
A8: 7 | B8: Mahesh | C8: 18 | D8: 19 | E8: 3 | F8: 10 | G8: 14 | H8: =SUM(C8:G8) -> 64 | I8: =AVERAGE(C8:G8) -> 12.8 | J8: =IF(I8>15,"A","B") -> B | M8: 7 | N8: COMPUTER | O8: 10 | P8: 25000 | Q8: =O8*P8 -> 250000 | R8: =IF(Q8>500000,"Expensive","Lets Buy it") -> Lets Buy it
A9: 8 | B9: Ashutosh | C9: 19 | D9: 20 | E9: 7 | F9: 14 | G9: 18 | H9: =SUM(C9:G9) -> 78 | I9: =AVERAGE(C9:G9) -> 15.6 | J9: =IF(I9>15,"A","B") -> A | M9: 8 | N9: KEYBOARD | O9: 5 | P9: 250 | Q9: =O9*P9 -> 1250 | R9: =IF(Q9>500000,"Expensive","Lets Buy it") -> Lets Buy it
A10: 9 | B10: Anil | C10: 22 | D10: 13 | E10: 8 | F10: 12 | G10: 19 | H10: =SUM(C10:G10) -> 74 | I10: =AVERAGE(C10:G10) -> 14.8 | J10: =IF(I10>15,"A","B") -> B | M10: 9 | N10: MOUSE | O10: 25 | P10: 100 | Q10: =O10*P10 -> 2500 | R10: =IF(Q10>500000,"Expensive","Lets Buy it") -> Lets Buy it
A11: 10 | B11: Prem | C11: 26 | D11: 12 | E11: 10 | F11: 11 | G11: 27 | H11: =SUM(C11:G11) -> 86 | I11: =AVERAGE(C11:G11) -> 17.2 | J11: =IF(I11>15,"A","B") -> A | M11: 10 | N11: PRINTER | O11: 30 | P11: 12000 | Q11: =O11*P11 -> 360000 | R11: =IF(Q11>500000,"Expensive","Lets Buy it") -> Lets Buy it
B13: A grade Count | C13: =COUNTIF(J2:J11,"A") -> 6
B14: B Grade Count | C14: =COUNTIF(J2:J11,"B") -> 4 | M14: How many items are there in a List | N14: =COUNTA(M2:M11) -> 10
B16: Count How many Students are there | C16: =COUNTA(A1:A11) -> 11 | M16: Calculate Item Computer Qty,Rate and Amount using Sumif | P16: =SUMIF(N2:N11,N8,O2:O11) -> 10 | Q16: =SUMIF(N2:N11,N8,P2:P11) -> 25000 | R16: =SUMIF(N2:N11,N8,Q2:Q11) -> 250000
B18: Student Ashok and Manoj Total No and Average | F18: =SUMIF(B2:B11,B3,H2:H11) -> 77 | G18: =SUMIF(B2:B11,B3,I2:I11) -> 15.4 | H18: =SUMIF(B2:B11,B4,H2:H11) -> 86 | I18: =AVERAGEIF(B2:B11,B4,I2:I11) -> 17.2 | M18: How many Items qty Greater than 20 | O18: =COUNTIF(O2:O11,">20") -> 3
M19: nd less than 20 | O19: =COUNTIF(O2:O11,"<20") -> 6
B20: How Many Students have Hindi & English Subject Number Greater Than > 20 and < 15 | C20: =COUNTIFS(C2:C11,">20",D2:D11,"<15") -> 3
B22: Subject | C22: 1st | D22: 2nd | E22: 3rd | F22: Total | G22: Average | H22: GRADE
B23: HINDI | C23: 20 | D23: 15 | E23: 20 | F23: =SUM(C23:E23) -> 55 | G23: =AVERAGE(C23:E23) -> 18.333333 | H23: =IF(G23>20,"A",IF(G23>15,"B","C")) -> B
B24: ENGLISH | C24: 30 | D24: 12 | E24: 15 | F24: =SUM(C24:E24) -> 57 | G24: =AVERAGE(C24:E24) -> 19 | H24: =IF(G24>20,"A",IF(G24>15,"B","C")) -> B
B25: MATH | C25: 15 | D25: 14 | E25: 14 | F25: =SUM(C25:E25) -> 43 | G25: =AVERAGE(C25:E25) -> 14.333333 | H25: =IF(G25>20,"A",IF(G25>15,"B","C")) -> C
B26: PHYSICS | C26: 12 | D26: 17 | E26: 17 | F26: =SUM(C26:E26) -> 46 | G26: =AVERAGE(C26:E26) -> 15.333333 | H26: =IF(G26>20,"A",IF(G26>15,"B","C")) -> B
B27: CHEMISTRY | C27: 14 | D27: 18 | E27: 18 | F27: =SUM(C27:E27) -> 50 | G27: =AVERAGE(C27:E27) -> 16.666667 | H27: =IF(G27>20,"A",IF(G27>15,"B","C")) -> B
B28: HISTORY | C28: 16 | D28: 25 | E28: 20 | F28: =SUM(C28:E28) -> 61 | G28: =AVERAGE(C28:E28) -> 20.333333 | H28: =IF(G28>20,"A",IF(G28>15,"B","C")) -> A
B29: GEO | C29: 18 | D29: 21 | E29: 22 | F29: =SUM(C29:E29) -> 61 | G29: =AVERAGE(C29:E29) -> 20.333333 | H29: =IF(G29>20,"A",IF(G29>15,"B","C")) -> A
B30: BIO | C30: 17 | D30: 23 | E30: 13 | F30: =SUM(C30:E30) -> 53 | G30: =AVERAGE(C30:E30) -> 17.666667 | H30: =IF(G30>20,"A",IF(G30>15,"B","C")) -> B
B31: BOTANY | C31: 20 | D31: 25 | E31: 25 | F31: =SUM(C31:E31) -> 70 | G31: =AVERAGE(C31:E31) -> 23.333333 | H31: =IF(G31>20,"A",IF(G31>15,"B","C")) -> A
B33: How many Subjects are there | C33: =COUNTA(B23:B31) -> 9
B34: How many Subject 1 Paper > 20 | C34: =COUNTIF(C23:C31,">20") -> 1
B36: Subject | C36: Total | D36: Grade | F36: Subject | G36: Total | H36: Average
B37: Hindi | C37: =VLOOKUP(B37,B22:H31,5,FALSE) -> 55 | D37: =VLOOKUP(B37,B22:H31,7,FALSE) -> B | F37: PHYSICS | G37: =VLOOKUP(F37,B22:H31,5,FALSE) -> 46 | H37: =VLOOKUP(F37,B22:H31,6,FALSE) -> 15.333333
B38: MATH | C38: =VLOOKUP(B38,B22:H31,5,FALSE) -> 43 | D38: =VLOOKUP(B38,B22:H31,7,FALSE) -> C | F38: MATH | G38: =VLOOKUP(F38,B22:H31,5,FALSE) -> 43 | H38: =VLOOKUP(F38,B22:H31,6,FALSE) -> 14.333333
B39: ENGLISH | C39: =VLOOKUP(B39,B22:H31,5,FALSE) -> 57 | D39: =VLOOKUP(B39,B22:H31,7,FALSE) -> B | F39: ENGLISH | G39: =VLOOKUP(F39,B22:H31,5,FALSE) -> 57 | H39: =VLOOKUP(F39,B22:H31,6,FALSE) -> 19

Sheet Salary Sheet
A1: NAME | B1: DEPARTMENT | C1: POST | D1: BASIC | E1: DA 2.5% | F1: HRA 3.5% | G1: PF 1.5% | H1: TOTAL | I1: GRADE
A2: RAM | B2: COMPUTER | C2: MANAGER | D2: 5000 | E2: =D2*2.5% -> 125 | F2: =D2*3.5% -> 175 | G2: =D2*1.5% -> 75 | H2: =SUM(D2:F2)-G2 -> 5225 | I2: =IF(H2>20000,"A",IF(H2>10000,"B","C")) -> C
A3: SHYAM | B3: COMPUTER | C3: SUPERVISOR | D3: 8000 | E3: =D3*2.5% -> 200 | F3: =D3*3.5% -> 280 | G3: =D3*1.5% -> 120 | H3: =D3+E3+F3-G3 -> 8360 | I3: =IF(H3>20000,"A",IF(H3>10000,"B","C")) -> C
A4: MANOJ | B4: COMPUTER | C4: PION | D4: 3000 | E4: =D4*2.5% -> 75 | F4: =D4*3.5% -> 105 | G4: =D4*1.5% -> 45 | H4: =D4+E4+F4-G4 -> 3135 | I4: =IF(H4>20000,"A",IF(H4>10000,"B","C")) -> C
A5: POOJA | B5: ELECTRICAL | C5: GUARD | D5: 6000 | E5: =D5*2.5% -> 150 | F5: =D5*3.5% -> 210 | G5: =D5*1.5% -> 90 | H5: =D5+E5+F5-G5 -> 6270 | I5: =IF(H5>20000,"A",IF(H5>10000,"B","C")) -> C
A6: RAHUL | B6: ELECTRICAL | C6: CASHER | D6: 8000 | E6: =D6*2.5% -> 200 | F6: =D6*3.5% -> 280 | G6: =D6*1.5% -> 120 | H6: =D6+E6+F6-G6 -> 8360 | I6: =IF(H6>20000,"A",IF(H6>10000,"B","C")) -> C
A7: RAKESH | B7: ELECTRICAL | C7: ACCOUNTANT | D7: 9000 | E7: =D7*2.5% -> 225 | F7: =D7*3.5% -> 315 | G7: =D7*1.5% -> 135 | H7: =D7+E7+F7-G7 -> 9405 | I7: =IF(H7>20000,"A",IF(H7>10000,"B","C")) -> C
A8: ASHISH | B8: FINANCE | C8: MANAGER | D8: 10000 | E8: =D8*2.5% -> 250 | F8: =D8*3.5% -> 350 | G8: =D8*1.5% -> 150 | H8: =D8+E8+F8-G8 -> 10450 | I8: =IF(H8>20000,"A",IF(H8>10000,"B","C")) -> B
A9: MANISH | B9: FINANCE | C9: GUARD | D9: 5000 | E9: =D9*2.5% -> 125 | F9: =D9*3.5% -> 175 | G9: =D9*1.5% -> 75 | H9: =D9+E9+F9-G9 -> 5225 | I9: =IF(H9>20000,"A",IF(H9>10000,"B","C")) -> C
A15: Name | B15: Post | C15: Grade
A16: MANOJ | B16: =VLOOKUP(A16,A1:I9,3,FALSE) -> PION | C16: =VLOOKUP(A16,A1:I9,9,FALSE) -> C
A17: ASHISH | B17: =VLOOKUP(A17,A1:I9,3,FALSE) -> MANAGER | C17: =VLOOKUP(A17,A1:I9,9,FALSE) -> B
A19: How many Employee is Manager and Guard | E19: =COUNTIF(C2:C9,"MANAGER") -> 2 | F19: =COUNTIF(C2:C9,"GUARD") -> 2

Sheet Sales Report
A1: SALESMAN | B1: JAN | C1: FEB | D1: MAR | E1: APR | F1: MAY | G1: JUN | H1: SALES | I1: TARGET | J1: RESULT
A2: RAMESH | B2: 2000 | C2: 1500 | D2: 300 | E2: 1400 | F2: 1000 | G2: 1400 | H2: =SUM(B2:G2) -> 7600 | I2: 10000 | J2: =IF(H2>I2,"Target Achieved","Not Achieved") -> Not Achieved
A3: RAKESH | B3: 5000 | C3: 1200 | D3: 500 | E3: 1200 | F3: 1200 | G3: 2800 | H3: =SUM(B3:G3) -> 11900 | I3: 12000 | J3: =IF(H3>I3,"Target Achieved","Not Achieved") -> Not Achieved
A4: RAHUL | B4: 3000 | C4: 800 | D4: 1200 | E4: 3000 | F4: 1500 | G4: 3500 | H4: =SUM(B4:G4) -> 13000 | I4: 18000 | J4: =IF(H4>I4,"Target Achieved","Not Achieved") -> Not Achieved
A5: POOJA | B5: 1000 | C5: 900 | D5: 1800 | E5: 5000 | F5: 1400 | G5: 1200 | H5: =SUM(B5:G5) -> 11300 | I5: 10000 | J5: =IF(H5>I5,"Target Achieved","Not Achieved") -> Target Achieved
A6: MANOJ | B6: 500 | C6: 1000 | D6: 2300 | E6: 8000 | F6: 1700 | G6: 1400 | H6: =SUM(B6:G6) -> 14900 | I6: 12000 | J6: =IF(H6>I6,"Target Achieved","Not Achieved") -> Target Achieved
A7: ASHOK | B7: 800 | C7: 500 | D7: 2400 | E7: 1900 | F7: 1800 | G7: 1800 | H7: =SUM(B7:G7) -> 9200 | I7: 10000 | J7: =IF(H7>I7,"Target Achieved","Not Achieved") -> Not Achieved
A8: AJEET | B8: 1200 | C8: 1400 | D8: 1500 | E8: 700 | F8: 2500 | G8: 7000 | H8: =SUM(B8:G8) -> 14300 | I8: 12000 | J8: =IF(H8>I8,"Target Achieved","Not Achieved") -> Target Achieved
A9: ALOK | B9: 1500 | C9: 1800 | D9: 1800 | E9: 1800 | F9: 300 | G9: 1500 | H9: =SUM(B9:G9) -> 8700 | I9: 10000 | J9: =IF(H9>I9,"Target Achieved","Not Achieved") -> Not Achieved
A10: AMRIT | B10: 1800 | C10: 2500 | D10: 1700 | E10: 1500 | F10: 2800 | G10: 1800 | H10: =SUM(B10:G10) -> 12100 | I10: 12000 | J10: =IF(H10>I10,"Target Achieved","Not Achieved") -> Target Achieved
A11: SURENDRA | B11: 200 | C11: 3000 | D11: 1900 | E11: 1200 | F11: 1500 | G11: 3000 | H11: =SUM(B11:G11) -> 10800 | I11: 10000 | J11: =IF(H11>I11,"Target Achieved","Not Achieved") -> Target Achieved
A12: SHASHI | B12: 1600 | C12: 1200 | D12: 2000 | E12: 800 | F12: 1700 | G12: 800 | H12: =SUM(B12:G12) -> 8100 | I12: 10000 | J12: =IF(H12>I12,"Target Achieved","Not Achieved") -> Not Achieved
B14: Target | C14: Result | F14: Count of no of salesman achieveing the target | H14: =COUNTIF(J2:J12,"Target Achieved") -> 5
A15: RAHUL | B15: =VLOOKUP(A15,A1:K12,9,FALSE) -> 18000 | C15: =VLOOKUP(A15,A1:K12,10,FALSE) -> Not Achieved | K15: =COUNT(A2:A12) -> 0
A16: POOJA | B16: =VLOOKUP(A16,A1:J12,9,FALSE) -> 10000 | C16: =VLOOKUP(A16,A1:J12,10,FALSE) -> Target Achieved | I16: Target | J16: Result
H17: AJEET | I17: =VLOOKUP(H17,A1:K12,9,FALSE) -> 12000 | J17: =VLOOKUP(H17,A1:K12,10,FALSE) -> Target Achieved

Sheet Sheet2
A1: NAME | B1: DATE OF BIRTH | C1: DAY | D1: MONTH | E1: YEAR
A2: RAMESH | B2: 29356 | C2: =DAY(B2) -> 15 | D2: =MONTH(B2) -> 5 | E2: =YEAR(B2) -> 1980
A3: RAKESH | B3: 29818 | C3: =DAY(B3) -> 20 | D3: =MONTH(B3) -> 8 | E3: =YEAR(B3) -> 1981
A4: RAHUL | B4: 37909 | C4: =DAY(B4) -> 15 | D4: =MONTH(B4) -> 10 | E4: =YEAR(B4) -> 2003
A5: POOJA | B5: 33018 | C5: =DAY(B5) -> 25 | D5: =MONTH(B5) -> 5 | E5: =YEAR(B5) -> 1990
A6: MANOJ | B6: 33840 | C6: =DAY(B6) -> 24 | D6: =MONTH(B6) -> 8 | E6: =YEAR(B6) -> 1992
A7: ASHOK | B7: 36030 | C7: =DAY(B7) -> 23 | D7: =MONTH(B7) -> 8 | E7: =YEAR(B7) -> 1998
A8: AJEET | B8: 29353 | C8: =DAY(B8) -> 12 | D8: =MONTH(B8) -> 5 | E8: =YEAR(B8) -> 1980
A9: ALOK | B9: 38429 | C9: =DAY(B9) -> 18 | D9: =MONTH(B9) -> 3 | E9: =YEAR(B9) -> 2005
A10: AMRIT | B10: 39309 | C10: =DAY(B10) -> 15 | D10: =MONTH(B10) -> 8 | E10: =YEAR(B10) -> 2007
A11: SURENDRA | B11: 40323 | C11: =DAY(B11) -> 25 | D11: =MONTH(B11) -> 5 | E11: =YEAR(B11) -> 2010
A12: SHASHI | B12: 34206 | C12: =DAY(B12) -> 25 | D12: =MONTH(B12) -> 8 | E12: =YEAR(B12) -> 1993
A14: How many Students are there | C14: =COUNTA(A2:A12) -> 11
A15: Student Surendra is how many years old | F15: =YEAR(TODAY()) - YEAR(B11) - (DATE(YEAR(TODAY()), MONTH(B11), DAY(B11)) > TODAY()) -> 15

Sheet Conditional Formatting
A1: ITEMS | B1: DATE | C1: COST
A2: BRAKES | B2: 42370 | C2: 800
A3: TYRES | B3: 42502 | C3: 2000
A4: BRAKES | B4: 42508 | C4: 500
A5: SERVICE | B5: 42510 | C5: 800
A6: SERVICE | B6: 42410 | C6: 1000
A7: WINDOW | B7: 42498 | C7: 1000
A8: TYRES | B8: 42500 | C8: 1200
A9: TYRES | B9: 42515 | C9: 1500
A10: CLUTCH | B10: 42561 | C10: 1800
A11: TYRES | B11: 42379 | C11: 2000
A12: CLUTCH | B12: 42536 | C12: 1500
A13: CLUTCH | B13: 42381 | C13: 1000
... A20: WINDOW | B20: 42602 | C20: 1800
A22: How many Items are there | C22: =COUNTA(A1:A20) -> 20
A23: How many brake,window and tyres have been boughts | C23: =COUNTIF(A2:A20,"BRAKES") -> 4 | D23: =COUNTIF(A2:A20,"TYRES") -> 5 | E23: =COUNTIF(A2:A20,"WINDOW") -> 5
A24: How many Items Cost is >1000 and below >=1000 | E24: =COUNTIFS(C1:C20,">1000",C1:C20,">=1000") -> 12
A25: Total Cost of Window and Brake Items | E25: =SUMIFS(C1:C20, A1:A20, "WINDOW") + SUMIFS(C1:C20, A1:A20, "BRAKES") -> 10800
A26: Highlight Tyre Items Between 500 and 2000 Cost
A28: Items Column is 15,18 and 20 Items Name

Sheet V Lookup
A1: Employee ID | B1: Full Name | C1: SSN | D1: Department | E1: Start Date | F1: Earnings
A2: EMP001 | B2: Faith K.Macias | C2: 845-04-3962 | D2: Marketing | E2: 39474 | F2: 73500
A3: EMP002 | B3: Lucian Q. Franklin | C3: 345-28-4935 | D3: IT/IS | E3: 39508 | F3: 80000 | L3: Employee ID | M3: Full Name | N3: SSN | O3: Department | P3: Start Date | Q3: Earnings
A4: EMP003 | B4: Blaze V. Bridges | C4: 503-53-8350 | D4: Marketing | E4: 39554 | F4: 95000 | L4: EMP001 | M4: =VLOOKUP(L4,A1:F15,2,FALSE) -> Faith K.Macias | N4: =VLOOKUP(L4,A1:F15,3,FALSE) -> 845-04-3962 | O4: =VLOOKUP(L4,A1:F15,4,FALSE) -> Marketing | P4: =VLOOKUP(L4,A1:F15,5,FALSE) -> 39474 | Q4: =VLOOKUP(L4,A1:G15,6,FALSE) -> 73500
A5: EMP004 | B5: Denton Q.Dale | C5: 858-39-7967 | D5: Marketing | E5: 39571 | F5: 105000 | L5: EMP002 | M5: =VLOOKUP(L5,A1:F15,2,FALSE) -> Lucian Q. Franklin | N5: =VLOOKUP(L5,A1:F15,3,FALSE) -> 345-28-4935 | O5: =VLOOKUP(L5,A1:F15,4,FALSE) -> IT/IS | P5: =VLOOKUP(L5,A1:F15,5,FALSE) -> 39508 | Q5: =VLOOKUP(L5,A1:F15,5,FALSE) -> 39508
A6: EMP005 | B6: Blossom K.Fox | C6: 245-18-5890 | D6: Engineering | E6: 39640 | F6: 90000 | L6: EMP003 | M6: =VLOOKUP(L6,A1:F15,2,FALSE) -> Blaze V. Bridges | N6: =VLOOKUP(L6,A1:F15,3,FALSE) -> 503-53-8350 | O6: =VLOOKUP(L6,A1:F15,4,FALSE) -> Marketing | P6: =VLOOKUP(L6,A1:F15,5,FALSE) -> 39554 | Q6: =VLOOKUP(L6,A1:F15,6,FALSE) -> 95000
A7: EMP006 | B7: Kerry V. David | C7: 873-45-8675 | D7: Finance | E7: 39646 | F7: 60000
A8: EMP007 | B8: Melanie X. Baker | C8: 190-08-3679 | D8: Finance | E8: 39726 | F8: 87000
A9: EMP008 | B9: Adele M. Fulton | C9: 352-36-9653 | D9: Engineering | E9: 39746 | F9: 104000
A10: EMP009 | B10: Justina O. Jensen | C10: 645-74-0451 | D10: Marketing | E10: 39757 | F10: 380050
A11: EMP010 | B11: Yoshi J. England | C11: 558-53-1475 | D11: Marketing | E11: 39791 | F11: 93000
A12: EMP011 | B12: Brooke Y. Mccarty | C12: 129-42-6148 | D12: IT/IS | E12: 39856 | F12: 180000
A13: EMP012 | B13: Kay G. Colon | C13: 796-50-4767 | D13: Marketing | E13: 39891 | F13: 100000
A14: EMP013 | B14: Callie I.Forbes | C14: 266-48-1339 | D14: Human Resources | E14: 39916 | F14: 136000
A15: EMP014 | B15: Zachery O.Mann | C15: 663-00-3285 | D15: Marketing | E15: 39931 | F15: 68000
A17: How many employees are there in a list | E17: =COUNTA(A2:A15) -> 14
A18: How many employees work in Finance and Marketing Department | E18: =SUMIF(D2:D15,"Finance",F2:F15)+SUMIF(D2:D15,"Marketing",F2:F15) -> 1061550 | F18: =COUNTIF(D2:D15,"Finance")+COUNTIF(D2:D15,"Marketing") -> 9
A19: How many amount earnings marketing department | E19: =SUMIF(D2:D15,"Marketing",F2:F15) -> 914550
B22: Full Name | C22: Department | D22: Earnings | F22: Full Name | G22: SSN
B23: Blossom K.Fox | C23: =VLOOKUP(B23,B1:F15,3,FALSE) -> Engineering | D23: =VLOOKUP(B23,B1:F15,5,FALSE) -> 90000 | F23: Blossom K.Fox | G23: =VLOOKUP(F23,B1:F15,2,FALSE) -> 245-18-5890

Sheet Excel Practise
A1: Product Name | B1: Jan | C1: Feb | D1: Mar | E1: Apr | F1: May | G1: Jun | H1: Jul | I1: Aug | J1: Total Sales | M1: Name | N1: Gender | O1: Country | P1: Score
A2: Apples | B2: 2773 | C2: 17462 | D2: 5954 | E2: 1348 | F2: 28158 | G2: 28799 | H2: 25415 | I2: 17277 | J2: =SUM(B2:I2) -> 127186 | M2: Richard | N2: Male | O2: United States | P2: 74
A3: Grapefruit | B3: 12908 | C3: 3083 | D3: 24492 | E3: 5825 | F3: 1080 | G3: 2188 | H3: 11087 | I3: 15544 | J3: =SUM(B3:I3) -> 76207 | M3: Jennifer | N3: Female | O3: United Kingdom | P3: 92
A4: Lemons | B4: 6554 | C4: 14262 | D4: 8377 | E4: 24982 | F4: 12184 | G4: 6430 | H4: 21159 | I4: 18597 | J4: =SUM(B4:I4) -> 112545 | M4: James | N4: Male | O4: United States | P4: 65
A5: Lime | B5: 28913 | C5: 1437 | D5: 20019 | E5: 13026 | F5: 26952 | G5: 27076 | H5: 7040 | I5: 10884 | J5: =SUM(B5:I5) -> 135347 | M5: Lisa | N5: Female | O5: Canada | P5: 82
A6: Oranges | B6: 4768 | C6: 7622 | D6: 28918 | E6: 27141 | F6: 3578 | G6: 10092 | H6: 15207 | I6: 12771 | J6: =SUM(B6:I6) -> 110097 | M6: Sharon | N6: Female | O6: Australia | P6: 50
A7: Peaches | B7: 13390 | C7: 3611 | D7: 6226 | E7: 27567 | F7: 29962 | G7: 2967 | H7: 5740 | I7: 2137 | J7: =SUM(B7:I7) -> 91600 | M7: Elizabeth | N7: Female | O7: Canada | P7: 91
A8: Pears | B8: 17585 | C8: 28508 | D8: 9614 | E8: 17110 | F8: 12143 | G8: 7365 | H8: 24185 | I8: 1643 | J8: =SUM(B8:I8) -> 118153 | M8: Carol | N8: Female | O8: United States | P8: 96
A9: Pineapples | B9: 22579 | C9: 16301 | D9: 6469 | E9: 22050 | F9: 8740 | G9: 18806 | H9: 3334 | I9: 3597 | J9: =SUM(B9:I9) -> 101876 | M9: Mark | N9: Male | O9: United States | P9: 58
M10: John | N10: Male | O10: Canada | P10: 67
M11: Susan | N11: Female | O11: United Kingdom | P11: 54
A12: How Many Fruits | B12: =COUNTA(A2:A9) -> 8 | M12: David | N12: Male | O12: United States | P12: 83
A14: Fruits | B14: Mar | C14: Jun | D14: Total Sales
A15: Lemons | B15: =VLOOKUP(A15,A1:J9,4,FALSE) -> 8377 | C15: =VLOOKUP(A15,A1:J9,7,FALSE) -> 6430 | D15: =VLOOKUP(A15,A1:J9,10,FALSE) -> 112545 | M15: How Many Male and Female Candiate in a List | O15: =COUNTIF(N2:N12,"Male") -> 5 | P15: =COUNTIF(N2:N12,"Female") -> 6
A16: Pineapples | B16: =VLOOKUP(A16,A1:J9,4,FALSE) -> 6469 | C16: =VLOOKUP(A16,A1:J9,6,FALSE) -> 8740 | D16: =VLOOKUP(A16,A1:J9,10,FALSE) -> 101876 | M16: How many employees are there in United States | O16: =COUNTIFS(N2:N12,"Male",O2:O12,"United States") -> 4
M18: Name | N18: Country
M19: Lisa | N19: =VLOOKUP(M19,M1:P12,3,FALSE) -> Canada
M20: John | N20: =VLOOKUP(M20,M1:P12,3,FALSE) -> Canada
M21: David | N21: =VLOOKUP(M21,M1:P12,3,FALSE) -> United States
M22: Sharon | N22: =VLOOKUP(M22,M1:P12,3,FALSE) -> Australia
A23: ID | B23: Brand | C23: Product | E23: ID | F23: Brand | G23: Product
A24: 101 | B24: Dell | C24: Computer | E24: 104 | F24: =VLOOKUP(E24,A23:C27,2,TRUE) -> HP | G24: =VLOOKUP(E24,$A$23:$C$27,3,FALSE) -> Printer
A25: 102 | B25: Logitech | C25: Keyboard | E25: 103 | F25: =VLOOKUP(E25,A23:C27,2,TRUE) -> Logitech | G25: =VLOOKUP(E25,$A$23:$C$27,3,FALSE) -> Mouse
A26: 103 | B26: Logitech | C26: Mouse | E26: 104 | F26: =VLOOKUP(E26,A23:C27,2,TRUE) -> HP | G26: =VLOOKUP(E26,$A$23:$C$27,3,FALSE) -> Printer
A27: 104 | B27: HP | C27: Printer | E27: 101 | F27: =VLOOKUP(E27,$A$23:$C$27,2,TRUE) -> Dell | G27: =VLOOKUP(E27,$A$23:$C$27,3,FALSE) -> Computer
E28: 102 | F28: =VLOOKUP(E28,$A$23:$C$27,2,TRUE) -> Logitech | G28: =VLOOKUP(E28,$A$23:$C$27,3,FALSE) -> Keyboard | L28: Region | M28: Jan | N28: Feb | O28: Mar | Q28: East | R28: Mar | S28: =INDEX($L$28:$O$32,MATCH(Q28,L28:L32,0),MATCH(R28,L28:O28,0)) -> #N/A
E29: 103 | F29: =VLOOKUP(E29,$A$23:$C$27,2,TRUE) -> Logitech | G29: =VLOOKUP(E29,$A$23:$C$27,3,FALSE) -> Mouse | L29: North | M29: 5535 | N29: 5414 | O29: 9027 | Q29: West | R29: Feb | S29: =INDEX($L$28:$O$32,MATCH(Q29,L29:L32,0),MATCH(R29,L28:O28,0)) -> 3858
E30: 101 | F30: =VLOOKUP(E30,$A$23:$C$27,2,TRUE) -> Dell | G30: =VLOOKUP(E30,$A$23:$C$27,3,FALSE) -> Computer | L30: South | M30: 5013 | N30: 5107 | O30: 11667 | Q30: South | R30: Jan | S30: =INDEX($L$28:$O$32,MATCH(Q30,L29:L32,0),MATCH(R30,L28:O28,0)) -> 5535
E31: 104 | F31: =VLOOKUP(E31,$A$23:$C$27,2,TRUE) -> HP | G31: =VLOOKUP(E31,$A$23:$C$27,3,FALSE) -> Printer | L31: East | M31: 6597 | N31: 3858 | O31: 1507 | Q31: North | R31: Mar | S31: =INDEX($L$28:$O$32,MATCH(Q31,L29:L32,0),MATCH(R31,L28:O28,0)) -> Mar
E32: 101 | F32: =VLOOKUP(E32,$A$23:$C$27,2,TRUE) -> Dell | G32: =VLOOKUP(E32,$A$23:$C$27,3,FALSE) -> Computer | L32: West | M32: 3195 | N32: 3654 | O32: 7225
E33: 102 | F33: =VLOOKUP(E33,$A$23:$C$27,2,TRUE) -> Logitech | G33: =VLOOKUP(E33,$A$23:$C$27,3,FALSE) -> Keyboard
A36: Emp Name | B36: Salary | C36: Department | D36: Emp ID | G36: Emp ID | H36: Salary | J36: Name | K36: PHYSICS | L36: CHEMISTRY | M36: MATHS | N36: BIOLOGY | O36: Passed The Exam? | R36: Date | S36: Emp Id | T36: Name | U36: Designation | V36: KRA
A37: Raju | B37: 92671 | C37: Sales | D37: Prd001 | G37: Prd001 | H37: =INDEX(B36:B56, MATCH(G37, D36:D56, 0)) -> 92671 | J37: NITIN | K37: PASS | L37: PASS | M37: FAIL | N37: PASS | O37: =IF(AND(K37="PASS",L37="PASS",M37="PASS",N37="PASS"),"Passed","Not Passed") -> Not Passed | R37: 43405 | S37: 1101 | T37: ARUN | U37: MIS-OPERATION | V37: SALES
A38: Ramesh | B38: 84120 | C38: Operations | D38: Prd002 | G38: Prd002 | H38: =INDEX(B36:B56,MATCH(G38,D36:D56,0)) -> 84120 | J38: FEROZ | K38: PASS | L38: PASS | M38: PASS | N38: PASS | O38: =IF(AND(K38="PASS",L38="PASS",M38="PASS",N38="PASS"),"Passed","Not Passed") -> Passed | R38: 43405 | S38: 1102 | T38: ASHOK | U38: OPERATION | V38: PHP
A39: Ramila | B39: 50793 | C39: Marketing | D39: Prd003 | G39: Prd003 | H39: =INDEX(B36:B56,MATCH(G39,D36:D56,0)) -> 50793 | J39: ANITHA | K39: PASS | L39: FAIL | M39: PASS | N39: PASS | O39: =IF(AND(K39="PASS",L39="PASS",M39="PASS",N39="PASS"),"Passed","Not Passed") -> Not Passed | R39: 43407 | S39: 1103 | T39: BISWAS | U39: SOFTWARE ENG | V39: JAVA
A40: Rajeshwari | B40: 77833 | C40: HR | D40: Prd004 | G40: Prd004 | H40: =INDEX($B$36:$B$56,MATCH(G40,$D$36:$D$56,0)) -> 77833 | J40: MADAN | K40: PASS | L40: PASS | M40: PASS | N40: PASS | O40: =IF(AND(K40="PASS",L40="PASS",M40="PASS",N40="PASS"),"Passed","Not Passed") -> Passed | R40: 43407 | S40: 1104 | T40: DINESH | U40: SME | V40: MAILS
A41: Karan | B41: 58914 | C41: Finance | D41: Prd005 | G41: Prd005 | H41: =INDEX($B$36:$B$56,MATCH(G41,$D$36:$D$56,0)) -> 58914 | J41: HARRY | K41: PASS | L41: FAIL | M41: PASS | N41: PASS | O41: =IF(AND(K41="PASS",L41="PASS",M41="PASS",N41="PASS"),"Passed","Not Passed") -> Not Passed | R41: 43407 | S41: 1105 | T41: ESHWAR | U41: PROGRAMMER | V41: C++
A42: Rohith | B42: 51096 | C42: IT | D42: Prd006 | G42: Prd006 | H42: =INDEX($B$36:$B$56,MATCH(G42,$D$36:$D$56,0)) -> 51096 | J42: SUMITH | K42: FAIL | L42: PASS | M42: PASS | N42: PASS | O42: =IF(AND(K42="PASS",L42="PASS",M42="PASS",N42="PASS"),"Passed","Not Passed") -> Not Passed | R42: 43410 | S42: 1106 | T42: FAHAD | U42: PROGRAMMER | V42: DOT NET
A43: Jacob | B43: 83735 | C43: Marketing | D43: Prd007 | G43: Prd007 | H43: =INDEX($B$36:$B$56,MATCH(G43,$D$36:$D$56,0)) -> 83735 | J43: HARSH | K43: PASS | L43: PASS | M43: PASS | N43: FAIL | O43: =IF(AND(K43="PASS",L43="PASS",M43="PASS",N43="PASS"),"Passed","Not Passed") -> Not Passed | R43: 43410 | S43: 1107 | T43: GANGA | U43: SOFTWARE ASSOCIATE | V43: TESTING
A44: Fleming | B44: 74418 | C44: IT | D44: Prd008 | G44: Prd008 | H44: =INDEX($B$36:$B$56,MATCH(G44,$D$36:$D$56,0)) -> 74418 | J44: TRIVEDI | K44: PASS | L44: PASS | M44: FAIL | N44: PASS | O44: =IF(AND(K44="PASS",L44="PASS",M44="PASS",N44="PASS"),"Passed","Not Passed") -> Not Passed | R44: 43412 | S44: 1108 | T44: HEMA | U44: NETWORK ENG | V44: SERVER
A45: Navya | B45: 51366 | C45: Sales | D45: Prd009 | G45: Prd009 | H45: =INDEX($B$36:$B$56,MATCH(G45,$D$36:$D$56,0)) -> 51366 | J45: ASHISH | K45: PASS | L45: PASS | M45: PASS | N45: PASS | O45: =IF(AND(K45="PASS",L45="PASS",M45="PASS",N45="PASS"),"Passed","Not Passed") -> Passed | R45: 43412 | S45: 1109 | T45: FARZANA | U45: SALES EXECUTIVE | V45: SALES
A46: Kavya | B46: 54600 | C46: Finance | D46: Prd010 | G46: Prd010 | H46: =INDEX($B$36:$B$56,MATCH(G46,$D$36:$D$56,0)) -> 54600 | R46: 43412 | S46: 1110 | T46: AYESH | U46: SALES EXECUTIVE | V46: AMAZON
A47: Santosh | B47: 93509 | C47: Operations | D47: Prd011 | G47: Prd011 | H47: =INDEX($B$36:$B$56,MATCH(G47,$D$36:$D$56,0)) -> 93509 | R47: 43413 | S47: 1111 | T47: PRAVEEN | U47: SALES EXECUTIVE | V47: AMAZON
A48: Shankar | B48: 80105 | C48: Finance | D48: Prd012 | G48: Prd012 | H48: =INDEX($B$36:$B$56,MATCH(G48,$D$36:$D$56,0)) -> 80105 | J48: Emp Id | K48: First Name | L48: Last Name | M48: Full Name | R48: 43413 | S48: 1109 | T48: FARZANA | U48: SALES EXECUTIVE | V48: AMAZON
A49: Rajesh | B49: 60802 | C49: Marketing | D49: Prd013 | G49: Prd013 | H49: =INDEX($B$36:$B$56,MATCH(G49,$D$36:$D$56,0)) -> 60802 | J49: D21 | K49: Vishal | L49: Mohan | M49: =CONCATENATE(K49," ",L49) -> Vishal Mohan | R49: 43414 | S49: 1112 | T49: VISHAL | U49: SALES EXECUTIVE | V49: GROFFERS
A50: Mahesh | B50: 76260 | C50: Sales | D50: Prd014 | G50: Prd014 | H50: =INDEX($B$36:$B$56,MATCH(G50,$D$36:$D$56,0)) -> 76260 | J50: D22 | K50: John | L50: Mathew | M50: =CONCATENATE(K50," ",L50) -> John Mathew | R50: 43414 | S50: 1113 | T50: VISHNU | U50: SALES EXECUTIVE | V50: PAYTM
A51: Hemaraj | B51: 88965 | C51: IT | D51: Prd015 | G51: Prd015 | H51: =INDEX($B$36:$B$56,MATCH(G51,$D$36:$D$56,0)) -> 88965 | J51: D23 | K51: Jamemah | L51: Powel | M51: =CONCATENATE(K51," ",L51) -> Jamemah Powel | R51: 43414 | S51: 1114 | T51: KRISHNA | U51: SALES EXECUTIVE | V51: PAYTM
A52: Nagaraj | B52: 63288 | C52: Operations | D52: Prd016 | G52: Prd016 | H52: =INDEX($B$36:$B$56,MATCH(G52,$D$36:$D$56,0)) -> 63288 | J52: D24 | K52: Arundathi | L52: Swaminathan | M52: =CONCATENATE(K52," ",L52) -> Arundathi Swaminathan | R52: 43414 | S52: 1115 | T52: ABHISHEK | U52: SALES EXECUTIVE | V52: MYNTRA
A53: Johnson | B53: 45742 | C53: Sales | D53: Prd017 | G53: Prd017 | H53: =INDEX($B$36:$B$56,MATCH(G53,$D$36:$D$56,0)) -> 45742 | J53: D25 | K53: Peter | L53: Potter | M53: =CONCATENATE(K53," ",L53) -> Peter Potter | R53: 43415 | S53: 1109 | T53: FARZANA | U53: SALES EXECUTIVE | V53: AMAZON
A54: David | B54: 88354 | C54: Marketing | D54: Prd018 | G54: Prd018 | H54: =INDEX($B$36:$B$56,MATCH(G54,$D$36:$D$56,0)) -> 88354 | J54: D26 | K54: Roger | L54: Williams | M54: =CONCATENATE(K54," ",L54) -> Roger Williams | R54: 43415 | S54: 1116 | T54: FARZANA BABU | U54: SALES EXECUTIVE | V54: MYNTRA
A55: Anderson | B55: 76641 | C55: Marketing | D55: Prd019 | G55: Prd019 | H55: =INDEX($B$36:$B$56,MATCH(G55,$D$36:$D$56,0)) -> 76641 | R55: 43415 | S55: 1116 | T55: FARZANA BABU | U55: SALES EXECUTIVE | V55: MYNTRA
A56: Peter | B56: 61678 | C56: Sales | D56: Prd020 | G56: Prd020 | H56: =INDEX($B$36:$B$56,MATCH(G56,$D$36:$D$56,0)) -> 61678
Q58: How Many Employees | S58: =COUNTA(T37:T55) -> 19
A59: How many employee in work HR,IT,Marketing Department | H59: =COUNTIF(C36:C56,"HR") -> 1 | I59: =COUNTIF(C36:C56,"Marketing") -> 5 | J59: =COUNTIF(C36:C56,"IT") -> 3 | Q59: How Many Employees In Sales Executive | S59: =COUNTIF(U37:U55,"SALES EXECUTIVE") -> 11
A60: Employee Santosh Salary | D60: =SUMIF(A36:A56,"Santosh",B36:B56) -> 93509 | Q60: How Many Employees In Sales Executive in Amzone and Myntra | S60: =COUNTIFS(U37:U55,"SALES EXECUTIVE",V37:V55,"AMAZON")+COUNTIFS(U37:U55,"SALES EXECUTIVE",V37:V55,"MYNTRA") -> 7
A61: IT and Marketing Department Total Salary | F61: =SUMIF(C36:C56,"IT",B36:B56) -> 214479 | G61: =SUMIF(C36:C56,"Marketing",B36:B56) -> 360325 | Q61: Name | R61: Department | S61: KRA
Q62: DINESH | R62: =VLOOKUP(Q62,T36:V55,2,FALSE) -> SME | S62: =VLOOKUP(Q62,T36:V55,3,FALSE) -> MAILS
Q63: VISHAL | R63: =VLOOKUP(Q63,T36:V55,2,FALSE) -> SALES EXECUTIVE | S63: =VLOOKUP(Q63,T36:V55,3,FALSE) -> GROFFERS
A65: Student Name | B65: Subject | E65: Result
A66: Name | B66: Maths | C66: English | D66: Physics | E66: Total | F66: Percentage | G66: Grade | J66: Product Name | K66: Units Sold | N66: Student | O66: Semester | P66: Score
A67: Alan | B67: 80 | C67: 75 | D67: 85 | E67: =SUM(B67:D67) -> 240 | F67: =AVERAGE(B67:D67) -> 80 | G67: =IF(F67>70,"Excellent",IF(F67>50,"Good","Bad")) -> Excellent | J67: A | K67: 250 | N67: John | O67: second | P67: 90
A68: Bob | B68: 50 | C68: 30 | D68: 40 | E68: =SUM(B68:D68) -> 120 | F68: =AVERAGE(B68:D68) -> 40 | G68: =IF(F68>70,"Excellent",IF(F68>50,"Good","Bad")) -> Bad | J68: D | K68: 110 | N68: gary | O68: Third | P68: 77
A69: Carol | B69: 60 | C69: 70 | D69: oor | E69: =SUM(B69:D69) -> 130 | F69: =AVERAGE(B69:D69) -> 65 | G69: =IF(F69>70,"Excellent",IF(F69>50,"Good","Bad")) -> Good | J69: E | K69: 300 | N69: Richa | O69: second | P69: 80
A70: David | B70: 90 | C70: 85 | D70: 95 | E70: =SUM(B70:D70) -> 270 | F70: =AVERAGE(B70:D70) -> 90 | G70: =IF(F70>70,"Excellent",IF(F70>50,"Good","Bad")) -> Excellent | J70: B | K70: 50 | N70: Hari | O70: second | P70: 65
A71: Eric | B71: 20 | C71: 30 | D71: Absent | E71: =SUM(B71:D71) -> 50 | F71: =AVERAGE(B71:D71) -> 25 | G71: =IF(F71>70,"Excellent",IF(F71>50,"Good","Bad")) -> Bad | J71: C | K71: 45 | N71: Tom | O71: Third | P71: 45
A72: Fried | B72: 40 | C72: 60 | D72: 80 | E72: =SUM(B72:D72) -> 180 | F72: =AVERAGE(B72:D72) -> 60 | G72: =IF(F72>70,"Excellent",IF(F72>50,"Good","Bad")) -> Good | J72: D | K72: 23 | N72: Will | O72: Third | P72: 55
A73: Gail | B73: 10 | C73: 90 | D73: 80 | E73: =SUM(B73:D73) -> 180 | F73: =AVERAGE(B73:D73) -> 60 | G73: =IF(F73>70,"Excellent",IF(F73>50,"Good","Bad")) -> Good | J73: F | K73: 25 | O73: Average of Semester Score
A74: Harry | B74: 80 | C74: 70 | D74: 60 | E74: =SUM(B74:D74) -> 210 | F74: =AVERAGE(B74:D74) -> 70 | G74: =IF(F74>70,"Excellent",IF(F74>50,"Good","Bad")) -> Good | J74: A | K74: 90 | N74: Second | O74: =AVERAGEIF(O67:O72,N74,P67:P72) -> 78.333333
A75: Ian | B75: 30 | C75: 10 | D75: 20 | E75: =SUM(B75:D75) -> 60 | F75: =AVERAGE(B75:D75) -> 20 | G75: =IF(F75>70,"Excellent",IF(F75>50,"Good","Bad")) -> Bad | J75: D | K75: 450 | N75: Third | O75: =AVERAGEIF(O67:O72,N75,P67:P72) -> 59
A76: Janice | B76: 10 | C76: 20 | D76: 30 | E76: =SUM(B76:D76) -> 60 | F76: =AVERAGE(B76:D76) -> 20 | G76: =IF(F76>70,"Excellent",IF(F76>50,"Good","Bad")) -> Bad | J76: C | K76: 23
J77: A | K77: 250
A78: How many Student | C78: =COUNTA(A67:A76) -> 10 | J78: B | K78: 25
A79: How many Student Percentage greater than 50 | F79: =COUNTIF(F67:F76,">50") -> 6 | N79: Zone | O79: City | P79: Sales | R79: Product Name | S79: Units Sold
A80: Student Bob and Eric Total Number | E80: =SUMIF(A67:A76,"Bob",E67:E76) -> 120 | F80: =SUMIF(A67:A76,"Eric",E67:E76) -> 50 | J80: Average of B | K80: =AVERAGEIF(J67:J78,"B",K67:K78) -> 37.5 | N80: South | O80: Chennai | P80: 25000 | R80: A | S80: 250
A81: How many student good and bad are there in this list | F81: =COUNTIF(G67:G76,"Good") -> 4 | G81: =COUNTIF(G67:G76,"Bad") -> 4 | J81: Average of D | K81: =AVERAGEIF(J67:J78,"D",K67:K78) -> 194.33333 | N81: East | O81: Patna | P81: 12000 | R81: D | S81: 110
J82: Average of C | K82: =AVERAGEIF(J67:J78,"C",K67:K78) -> 34 | N82: North | O82: Delhi | P82: 4200 | R82: E | S82: 300
J83: Average of A | K83: =AVERAGEIF(J67:J78,"A",K67:K78) -> 196.66667 | N83: North | O83: Kanpur | P83: 5600 | R83: B | S83: 50
N84: West | O84: Gandhinagar | P84: 15000 | R84: C | S84: 45
N85: East | O85: Hubli | P85: 7000 | R85: D | S85: 23
N86: South | O86: Mangalore | P86: 5200 | R86: F | S86: 25
N87: North | O87: Chandigarh | P87: 6000 | R87: A | S87: 90
N88: West | O88: Pune | P88: 8500 | R88: D | S88: 450
N89: South | O89: Hyderabad | P89: 12000 | R89: C | S89: 23
N90: North | O90: Meerut | P90: 4300 | R90: A | S90: 250
N91: West | O91: Nagpur | P91: 1200 | R91: B | S91: 25
N93: Average of West Zone | P93: =AVERAGEIF(N80:N91,"West",P80:P91) -> 8233.3333 | R93: Average of Units Sold above 250 | U93: =AVERAGEIF(S80:S91,">250",S80:S91) -> 375
N94: Average of East Zone | P94: =AVERAGEIF(N80:N91,"East",P80:P91) -> 9500 | R94: Avergae of Units Sold below 100 | U94: =AVERAGEIF(S80:S91,"<100",S80:S91) -> 40.142857
N95: Average of North Zone | P95: =AVERAGEIF(N80:N91,"North",P80:P91) -> 5025
N96: Average of South Zone | P96: =AVERAGEIF(N80:N91,"South",P80:P91) -> 14066.667

Sheet Vlookup Table
A1: Emp Id | B1: First Name | C1: Last Name | D1: Department | E1: Location
A2: 101 | B2: Donald | C2: Patrick | D2: Finance | E2: Bangalore
A3: 102 | B3: Samuel | C3: Samson | D3: Marketing | E3: Hyderabad
A4: 103 | B4: Ian | C4: Jacob | D4: Finance | E4: Hyderabad
A5: 104 | B5: David | C5: Johnson | D5: Marketing | E5: Pune
A6: 105 | B6: Ian | C6: Smith | D6: Marketing | E6: Bangalore
A7: 106 | B7: Henry | C7: Madrid | D7: IT | E7: Pune
A8: 107 | B8: Ronica | C8: Brave | D8: Finance | E8: Hyderabad
A9: 108 | B9: Christine | C9: Salvi | D9: Marketing | E9: Bangalore
A10: 109 | B10: Andrew | C10: Baisley | D10: IT | E10: Hyderabad
A11: 110 | B11: Erica | C11: Irons | D11: IT | E11: Pune
K13: Dept | L13: Incentive | M13: Bonus | O13: Region | P13: TA
A14: Emp | B14: First Name | C14: Dept | D14: Region | E14: Salary | F14: Incentive | G14: Bonus | H14: TA | K14: Sales | L14: 100 | M14: 900 | O14: north | P14: 100
A15: 1 | B15: Raja | C15: Sales | D15: north | E15: 15625 | F15: =VLOOKUP(C15,$K$13:$M$21,2,FALSE) -> 100 | G15: =VLOOKUP(C15,$K$13:$M$21,3,FALSE) -> 900 | H15: =VLOOKUP(D15,$O$13:$P$17,2,FALSE) -> 100 | I15: =IF(E15>15000,"A",IF(E15>10000,"B","C")) -> A | K15: Mktg | L15: 200 | M15: 800 | O15: south | P15: 200
A16: 2 | B16: Suman | C16: Sales | D16: east | E16: 12500 | F16: =VLOOKUP(C16,$K$13:$M$21,2,FALSE) -> 100 | G16: =VLOOKUP(C16,$K$13:$M$21,3,FALSE) -> 900 | H16: =VLOOKUP(D16,$O$13:$P$17,2,FALSE) -> 300 | I16: =IF(E16>15000,"A",IF(E16>10000,"B","C")) -> B | K16: R&D | L16: 300 | M16: 700 | O16: east | P16: 300
A17: 3 | B17: Beena | C17: Mktg | D17: north | E17: 8750 | F17: =VLOOKUP(C17,$K$13:$M$21,2,FALSE) -> 200 | G17: =VLOOKUP(C17,$K$13:$M$21,3,FALSE) -> 800 | H17: =VLOOKUP(D17,$O$13:$P$17,2,FALSE) -> 100 | I17: =IF(E17>15000,"A",IF(E17>10000,"B","C")) -> C | K17: Finance | L17: 400 | M17: 600 | O17: west | P17: 400
A18: 4 | B18: Seema | C18: R&D | D18: north | E18: 15000 | F18: =VLOOKUP(C18,$K$13:$M$21,2,FALSE) -> 300 | G18: =VLOOKUP(C18,$K$13:$M$21,3,FALSE) -> 700 | H18: =VLOOKUP(D18,$O$13:$P$17,2,FALSE) -> 100 | I18: =IF(E18>15000,"A",IF(E18>10000,"B","C")) -> B | K18: Admin | L18: 500 | M18: 500
A19: 5 | B19: Julie | C19: R&D | D19: north | E19: 8875 | F19: =VLOOKUP(C19,$K$13:$M$21,2,FALSE) -> 300 | G19: =VLOOKUP(C19,$K$13:$M$21,3,FALSE) -> 700 | H19: =VLOOKUP(D19,$O$13:$P$17,2,FALSE) -> 100 | I19: =IF(E19>15000,"A",IF(E19>10000,"B","C")) -> C | K19: Director | L19: 600 | M19: 400
A20: 6 | B20: Neena | C20: Sales | D20: north | E20: 8875 | F20: =VLOOKUP(C20,$K$13:$M$21,2,FALSE) -> 100 | G20: =VLOOKUP(C20,$K$13:$M$21,3,FALSE) -> 900 | H20: =VLOOKUP(D20,$O$13:$P$17,2,FALSE) -> 100 | I20: =IF(E20>15000,"A",IF(E20>10000,"B","C")) -> C | K20: Personal | L20: 700 | M20: 300
A21: 7 | B21: Pankaj | C21: Mktg | D21: north | E21: 10625 | F21: =VLOOKUP(C21,$K$13:$M$21,2,FALSE) -> 200 | G21: =VLOOKUP(C21,$K$13:$M$21,3,FALSE) -> 800 | H21: =VLOOKUP(D21,$O$13:$P$17,2,FALSE) -> 100 | I21: =IF(E21>15000,"A",IF(E21>10000,"B","C")) -> B | K21: CCD | L21: 800 | M21: 200
A22: 8 | B22: Andre | C22: Finance | D22: east | E22: 11250 | F22: =VLOOKUP(C22,$K$13:$M$21,2,FALSE) -> 400 | G22: =VLOOKUP(C22,$K$13:$M$21,3,FALSE) -> 600 | H22: =VLOOKUP(D22,$O$13:$P$17,2,FALSE) -> 300 | I22: =IF(E22>15000,"A",IF(E22>10000,"B","C")) -> B
A23: 9 | B23: Sujay | C23: Admin | D23: west | E23: 10625 | F23: =VLOOKUP(C23,$K$13:$M$21,2,FALSE) -> 500 | G23: =VLOOKUP(C23,$K$13:$M$21,3,FALSE) -> 500 | H23: =VLOOKUP(D23,$O$13:$P$17,2,FALSE) -> 400 | I23: =IF(E23>15000,"A",IF(E23>10000,"B","C")) -> B
A24: 10 | B24: Shilpa | C24: Finance | D24: north | E24: 15000 | F24: =VLOOKUP(C24,$K$13:$M$21,2,FALSE) -> 400 | G24: =VLOOKUP(C24,$K$13:$M$21,3,FALSE) -> 600 | H24: =VLOOKUP(D24,$O$13:$P$17,2,FALSE) -> 100 | I24: =IF(E24>15000,"A",IF(E24>10000,"B","C")) -> B
A25: 11 | B25: Meera | C25: Admin | D25: east | E25: 13750 | F25: =VLOOKUP(C25,$K$13:$M$21,2,FALSE) -> 500 | G25: =VLOOKUP(C25,$K$13:$M$21,3,FALSE) -> 500 | H25: =VLOOKUP(D25,$O$13:$P$17,2,FALSE) -> 300 | I25: =IF(E25>15000,"A",IF(E25>10000,"B","C")) -> B | K25: How many employee are there in sales and mktg department | Q25: =COUNTIF(C15:C31,"Sales") -> 3 | R25: =COUNTIF(C15:C31,"Mktg") -> 3
A26: 12 | B26: Sheetal | C26: Director | D26: south | E26: 35000 | F26: =VLOOKUP(C26,$K$13:$M$21,2,FALSE) -> 600 | G26: =VLOOKUP(C26,$K$13:$M$21,3,FALSE) -> 400 | H26: =VLOOKUP(D26,$O$13:$P$17,2,FALSE) -> 200 | I26: =IF(E26>15000,"A",IF(E26>10000,"B","C")) -> A | K26: How many salary in sales department | P26: =SUMIF(C15:C31,"Sales",E15:E31) -> 37000
A27: 13 | B27: K.Sita | C27: Personal | D27: north | E27: 10625 | F27: =VLOOKUP(C27,$K$13:$M$21,2,FALSE) -> 700 | G27: =VLOOKUP(C27,$K$13:$M$21,3,FALSE) -> 300 | H27: =VLOOKUP(D27,$O$13:$P$17,2,FALSE) -> 100 | I27: =IF(E27>15000,"A",IF(E27>10000,"B","C")) -> B | K27: How many employee department sales ,North Region Salary | R27: =SUMIFS(E15:E30,C15:C31,"Sales",D15:D31,"north") -> #VALUE!
A28: 14 | B28: Priya | C28: Personal | D28: north | E28: 10625 | F28: =VLOOKUP(C28,$K$13:$M$21,2,FALSE) -> 700 | G28: =VLOOKUP(C28,$K$13:$M$21,3,FALSE) -> 300 | H28: =VLOOKUP(D28,$O$13:$P$17,2,FALSE) -> 100 | I28: =IF(E28>15000,"A",IF(E28>10000,"B","C")) -> B | K28: How many employee department sales and Region North | R28: =COUNTIFS(C15:C31,"Sales",D15:D31,"north") -> 2
A29: 15 | B29: Aalok | C29: Admin | D29: east | E29: 11250 | F29: =VLOOKUP(C29,$K$13:$M$21,2,FALSE) -> 500 | G29: =VLOOKUP(C29,$K$13:$M$21,3,FALSE) -> 500 | H29: =VLOOKUP(D29,$O$13:$P$17,2,FALSE) -> 300 | I29: =IF(E29>15000,"A",IF(E29>10000,"B","C")) -> B | K29: If Salary Greater Than 15000 "A",If salary Greater than 10000 "B" otherwise "C"
A30: 16 | B30: Aakash | C30: Admin | D30: west | E30: 11250 | F30: =VLOOKUP(C30,$K$13:$M$21,2,FALSE) -> 500 | G30: =VLOOKUP(C30,$K$13:$M$21,3,FALSE) -> 500 | H30: =VLOOKUP(D30,$O$13:$P$17,2,FALSE) -> 400 | I30: =IF(E30>15000,"A",IF(E30>10000,"B","C")) -> B
A31: 17 | B31: Parvati | C31: Mktg | D31: north | E31: 7500 | F31: =VLOOKUP(C31,$K$13:$M$21,2,FALSE) -> 200 | G31: =VLOOKUP(C31,$K$13:$M$21,3,FALSE) -> 800 | H31: =VLOOKUP(D31,$O$13:$P$17,2,FALSE) -> 100 | I31: =IF(E31>15000,"A",IF(E31>10000,"B","C")) -> C

Sheet Solution
A1: Emp Id | B1: First Name | C1: Last Name | D1: Department | E1: Location
A2: 101 | B2: =VLOOKUP(A2,'Vlookup Table'!$A$1:$E$11,2,FALSE) -> Donald | C2: =VLOOKUP(A2,'Vlookup Table'!$A$1:$E$11,3,FALSE) -> Patrick | D2: =VLOOKUP(A2,'Vlookup Table'!$A$1:E11,4,FALSE) -> Finance | E2: =VLOOKUP(A2,'Vlookup Table'!$A$1:$E$11,5,FALSE) -> Bangalore
A3: 102 | B3: =VLOOKUP(A3,'Vlookup Table'!$A$1:$E$11,2,FALSE) -> Samuel | C3: =VLOOKUP(A3,'Vlookup Table'!$A$1:$E$11,3,FALSE) -> Samson | D3: =VLOOKUP(A3,'Vlookup Table'!$A$1:E12,4,FALSE) -> Marketing | E3: =VLOOKUP(A3,'Vlookup Table'!$A$1:$E$11,5,FALSE) -> Hyderabad
A4: 103 | B4: =VLOOKUP(A4,'Vlookup Table'!$A$1:$E$11,2,FALSE) -> Ian | C4: =VLOOKUP(A4,'Vlookup Table'!$A$1:$E$11,3,FALSE) -> Jacob | D4: =VLOOKUP(A4,'Vlookup Table'!$A$1:E13,4,FALSE) -> Finance | E4: =VLOOKUP(A4,'Vlookup Table'!$A$1:$E$11,5,FALSE) -> Hyderabad
A5: 104 | B5: =VLOOKUP(A5,'Vlookup Table'!$A$1:$E$11,2,FALSE) -> David | C5: =VLOOKUP(A5,'Vlookup Table'!$A$1:$E$11,3,FALSE) -> Johnson | D5: =VLOOKUP(A5,'Vlookup Table'!$A$1:E14,4,FALSE) -> Marketing | E5: =VLOOKUP(A5,'Vlookup Table'!$A$1:$E$11,5,FALSE) -> Pune
A6: 105 | B6: =VLOOKUP(A6,'Vlookup Table'!$A$1:$E$11,2,FALSE) -> Ian | C6: =VLOOKUP(A6,'Vlookup Table'!$A$1:$E$11,3,FALSE) -> Smith | D6: =VLOOKUP(A6,'Vlookup Table'!$A$1:E15,4,FALSE) -> Marketing | E6: =VLOOKUP(A6,'Vlookup Table'!$A$1:$E$11,5,FALSE) -> Bangalore
A7: 106 | B7: =VLOOKUP(A7,'Vlookup Table'!$A$1:$E$11,2,FALSE) -> Henry | C7: =VLOOKUP(A7,'Vlookup Table'!$A$1:$E$11,3,FALSE) -> Madrid | D7: =VLOOKUP(A7,'Vlookup Table'!$A$1:E16,4,FALSE) -> IT | E7: =VLOOKUP(A7,'Vlookup Table'!$A$1:$E$11,5,FALSE) -> Pune
A8: 107 | B8: =VLOOKUP(A8,'Vlookup Table'!$A$1:$E$11,2,FALSE) -> Ronica | C8: =VLOOKUP(A8,'Vlookup Table'!$A$1:$E$11,3,FALSE) -> Brave | D8: =VLOOKUP(A8,'Vlookup Table'!$A$1:E17,4,FALSE) -> Finance | E8: =VLOOKUP(A8,'Vlookup Table'!$A$1:$E$11,5,FALSE) -> Hyderabad
A9: 108 | B9: =VLOOKUP(A9,'Vlookup Table'!$A$1:$E$11,2,FALSE) -> Christine | C9: =VLOOKUP(A9,'Vlookup Table'!$A$1:$E$11,3,FALSE) -> Salvi | D9: =VLOOKUP(A9,'Vlookup Table'!$A$1:E18,4,FALSE) -> Marketing | E9: =VLOOKUP(A9,'Vlookup Table'!$A$1:$E$11,5,FALSE) -> Bangalore
A10: 109 | B10: =VLOOKUP(A10,'Vlookup Table'!$A$1:$E$11,2,FALSE) -> Andrew | C10: =VLOOKUP(A10,'Vlookup Table'!$A$1:$E$11,3,FALSE) -> Baisley | D10: =VLOOKUP(A10,'Vlookup Table'!$A$1:E19,4,FALSE) -> IT | E10: =VLOOKUP(A10,'Vlookup Table'!$A$1:$E$11,5,FALSE) -> Hyderabad
A11: 110 | B11: =VLOOKUP(A11,'Vlookup Table'!$A$1:$E$11,2,FALSE) -> Erica | C11: =VLOOKUP(A11,'Vlookup Table'!$A$1:$E$11,3,FALSE) -> Irons | D11: =VLOOKUP(A11,'Vlookup Table'!$A$1:E20,4,FALSE) -> IT | E11: =VLOOKUP(A11,'Vlookup Table'!$A$1:$E$11,5,FALSE) -> Pune

Sheet Sheet3
A1: OrderId | B1: Product | C1: Category | D1: Amount | E1: Date | F1: Country
A2: 1 | B2: Carrots | C2: Vegetables | D2: 4270 | E2: 42375 | F2: United States
A3: 2 | B3: Broccoli | C3: Vegetables | D3: 8239 | E3: 42376 | F3: United Kingdom | J3: How many Fruit and Vegetables Items in a list | O3: =COUNTIF(C2:C31,"Fruit") -> 18 | P3: =COUNTIF(C2:C31,"Vegetables") -> 12 | Q3: =COUNTIFS(C2:C31,"Fruit",C2:C31,"Vegetables") -> 0
A4: 3 | B4: Banana | C4: Fruit | D4: 617 | E4: 42377 | F4: United States | J4: Total Apple and Banana Amount | N4: =SUMIF(B2:B31,"Apple",D2:D31) -> 25557 | O4: =SUMIF(B2:B31,"Banana",D2:D31) -> 38956
A5: 4 | B5: Banana | C5: Fruit | D5: 8384 | E5: 42379 | F5: Canada | J5: How many products are there in a list | N5: =COUNTA(B2:B31) -> 30
A6: 5 | B6: Beans | C6: Vegetables | D6: 2626 | E6: 42379 | F6: Germany
A7: 6 | B7: Orange | C7: Fruit | D7: 3610 | E7: 42380 | F7: United States
A8: 7 | B8: Broccoli | C8: Vegetables | D8: 9062 | E8: 42380 | F8: Australia
A9: 8 | B9: Banana | C9: Fruit | D9: 6906 | E9: 42385 | F9: New Zealand
A10: 9 | B10: Apple | C10: Fruit | D10: 2417 | E10: 42385 | F10: France
A11: 10 | B11: Apple | C11: Fruit | D11: 7431 | E11: 42385 | F11: Canada
A12: 11 | B12: Banana | C12: Fruit | D12: 8250 | E12: 42385 | F12: Germany
A13: 12 | B13: Broccoli | C13: Vegetables | D13: 7012 | E13: 42387 | F13: United States
A14: 13 | B14: Carrots | C14: Vegetables | D14: 1903 | E14: 42389 | F14: Germany
A15: 14 | B15: Broccoli | C15: Vegetables | D15: 2824 | E15: 42391 | F15: Canada
A16: 15 | B16: Apple | C16: Fruit | D16: 6946 | E16: 42393 | F16: France
A17: 16 | B17: Banana | C17: Fruit | D17: 2320 | E17: 42396 | F17: United Kingdom
... A31: 30 | B31: Apple | C31: Fruit | D31: 7602 | E31: 42421 | F31: France
